<OpenViBE-Scenario>
	<Boxes>
		<Box>
			<Identifier>(0x081fe9aa, 0x731358b8)</Identifier>
			<Name>Generic stream reader</Name>
			<AlgorithmClassIdentifier>(0x6468099f, 0x0370095a)</AlgorithmClassIdentifier>
			<Outputs>
				<Output>
					<TypeIdentifier>(0x403488e7, 0x565d70b6)</TypeIdentifier>
					<Name>Output stream 1</Name>
				</Output>
				<Output>
					<TypeIdentifier>(0x5ba36127, 0x195feae1)</TypeIdentifier>
					<Name>Output stream 2</Name>
				</Output>
				<Output>
					<TypeIdentifier>(0x6f752dd0, 0x082a321e)</TypeIdentifier>
					<Name>Output stream 3</Name>
				</Output>
			</Outputs>
			<Settings>
				<Setting>
					<TypeIdentifier>(0x330306dd, 0x74a95f98)</TypeIdentifier>
					<Name>Filename</Name>
					<DefaultValue></DefaultValue>
					<Value>${externalP300_TrainFile}</Value>
					<Modifiability>false</Modifiability>
				</Setting>
			</Settings>
			<Attributes>
				<Attribute>
					<Identifier>(0x17ee7c08, 0x94c14893)</Identifier>
					<Value></Value>
				</Attribute>
				<Attribute>
					<Identifier>(0x1fa7a38f, 0x54edbe0b)</Identifier>
					<Value>-624</Value>
				</Attribute>
				<Attribute>
					<Identifier>(0x1fa963f5, 0x1a638cd4)</Identifier>
					<Value>48</Value>
				</Attribute>
				<Attribute>
					<Identifier>(0x207c9054, 0x3c841b63)</Identifier>
					<Value>192</Value>
				</Attribute>
				<Attribute>
					<Identifier>(0x30a4e5c9, 0x83502953)</Identifier>
					<Value></Value>
				</Attribute>
				<Attribute>
					<Identifier>(0x4e7b798a, 0x183beafb)</Identifier>
					<Value>(0xf37b8e7a, 0x1bc33e4e)</Value>
				</Attribute>
				<Attribute>
					<Identifier>(0xad100179, 0xa3c984ab)</Identifier>
					<Value>166</Value>
				</Attribute>
				<Attribute>
					<Identifier>(0xc80ce8af, 0xf699f813)</Identifier>
					<Value>1</Value>
				</Attribute>
				<Attribute>
					<Identifier>(0xce18836a, 0x9c0eb403)</Identifier>
					<Value>1</Value>
				</Attribute>
			</Attributes>
		</Box>
		<Box>
			<Identifier>(0x08e4d38b, 0x2814b4fc)</Identifier>
			<Name>Player Controller</Name>
			<AlgorithmClassIdentifier>(0x5f426dce, 0x08456e13)</AlgorithmClassIdentifier>
			<Inputs>
				<Input>
					<TypeIdentifier>(0x6f752dd0, 0x082a321e)</TypeIdentifier>
					<Name>Stimulations</Name>
				</Input>
			</Inputs>
			<Settings>
				<Setting>
					<TypeIdentifier>(0x2c132d6e, 0x44ab0d97)</TypeIdentifier>
					<Name>Stimulation name</Name>
					<DefaultValue>OVTK_StimulationId_Label_00</DefaultValue>
					<Value>OVTK_StimulationId_ExperimentStop</Value>
					<Modifiability>false</Modifiability>
				</Setting>
				<Setting>
					<TypeIdentifier>(0xcc14d8d6, 0xf27ecb73)</TypeIdentifier>
					<Name>Action to perform</Name>
					<DefaultValue>Pause</DefaultValue>
					<Value>Stop</Value>
					<Modifiability>false</Modifiability>
				</Setting>
			</Settings>
			<Attributes>
				<Attribute>
					<Identifier>(0x1fa7a38f, 0x54edbe0b)</Identifier>
					<Value>-432</Value>
				</Attribute>
				<Attribute>
					<Identifier>(0x1fa963f5, 0x1a638cd4)</Identifier>
					<Value>31</Value>
				</Attribute>
				<Attribute>
					<Identifier>(0x207c9054, 0x3c841b63)</Identifier>
					<Value>704</Value>
				</Attribute>
				<Attribute>
					<Identifier>(0x4e7b798a, 0x183beafb)</Identifier>
					<Value>(0x568d148e, 0x650792b3)</Value>
				</Attribute>
				<Attribute>
					<Identifier>(0xad100179, 0xa3c984ab)</Identifier>
					<Value>131</Value>
				</Attribute>
				<Attribute>
					<Identifier>(0xce18836a, 0x9c0eb403)</Identifier>
					<Value>2</Value>
				</Attribute>
				<Attribute>
					<Identifier>(0xcfad85b0, 0x7c6d841c)</Identifier>
					<Value>1</Value>
				</Attribute>
			</Attributes>
		</Box>
		<Box>
			<Identifier>(0x1c9d2a5e, 0x10945cc3)</Identifier>
			<Name>xDAWN Spatial Filter</Name>
			<AlgorithmClassIdentifier>(0xdd332c6c, 0x195b4fd4)</AlgorithmClassIdentifier>
			<Inputs>
				<Input>
					<TypeIdentifier>(0x5ba36127, 0x195feae1)</TypeIdentifier>
					<Name>Input Signal</Name>
				</Input>
			</Inputs>
			<Outputs>
				<Output>
					<TypeIdentifier>(0x5ba36127, 0x195feae1)</TypeIdentifier>
					<Name>Output Signal</Name>
				</Output>
			</Outputs>
			<Settings>
				<Setting>
					<TypeIdentifier>(0x79a9edeb, 0x245d83fc)</TypeIdentifier>
					<Name>Spatial Fitler Coefficients</Name>
					<DefaultValue>1;0;0;0;0;1;0;0;0;0;1;0;0;0;0;1</DefaultValue>
					<Value>1;0;0;0;0;1;0;0;0;0;1;0;0;0;0;1</Value>
					<Modifiability>false</Modifiability>
				</Setting>
				<Setting>
					<TypeIdentifier>(0x007deef9, 0x2f3e95c6)</TypeIdentifier>
					<Name>Number of Output Channels</Name>
					<DefaultValue>4</DefaultValue>
					<Value>4</Value>
					<Modifiability>false</Modifiability>
				</Setting>
				<Setting>
					<TypeIdentifier>(0x007deef9, 0x2f3e95c6)</TypeIdentifier>
					<Name>Number of Input Channels</Name>
					<DefaultValue>4</DefaultValue>
					<Value>4</Value>
					<Modifiability>false</Modifiability>
				</Setting>
			</Settings>
			<Attributes>
				<Attribute>
					<Identifier>(0x1fa7a38f, 0x54edbe0b)</Identifier>
					<Value>-336</Value>
				</Attribute>
				<Attribute>
					<Identifier>(0x1fa963f5, 0x1a638cd4)</Identifier>
					<Value>65</Value>
				</Attribute>
				<Attribute>
					<Identifier>(0x207c9054, 0x3c841b63)</Identifier>
					<Value>192</Value>
				</Attribute>
				<Attribute>
					<Identifier>(0x30a4e5c9, 0x83502953)</Identifier>
					<Value></Value>
				</Attribute>
				<Attribute>
					<Identifier>(0x4e7b798a, 0x183beafb)</Identifier>
					<Value>(0x74d8d3ca, 0x2c7b1995)</Value>
				</Attribute>
				<Attribute>
					<Identifier>(0x527ad68d, 0x16d746a0)</Identifier>
					<Value></Value>
				</Attribute>
				<Attribute>
					<Identifier>(0x8d21ff41, 0xdf6afe7e)</Identifier>
					<Value>${Player_ScenarioDirectory}/${externalP300_paramFile}-spatial-filter.cfg</Value>
				</Attribute>
				<Attribute>
					<Identifier>(0xac367a9c, 0x2da95abe)</Identifier>
					<Value>68</Value>
				</Attribute>
				<Attribute>
					<Identifier>(0xad100179, 0xa3c984ab)</Identifier>
					<Value>163</Value>
				</Attribute>
				<Attribute>
					<Identifier>(0xc80ce8af, 0xf699f813)</Identifier>
					<Value>1</Value>
				</Attribute>
				<Attribute>
					<Identifier>(0xce18836a, 0x9c0eb403)</Identifier>
					<Value>3</Value>
				</Attribute>
				<Attribute>
					<Identifier>(0xcfad85b0, 0x7c6d841c)</Identifier>
					<Value>1</Value>
				</Attribute>
			</Attributes>
		</Box>
		<Box>
			<Identifier>(0x283e849b, 0x6ccb375a)</Identifier>
			<Name>Temporal filter - GPL</Name>
			<AlgorithmClassIdentifier>(0xb4f9d042, 0x9d79f2e5)</AlgorithmClassIdentifier>
			<Inputs>
				<Input>
					<TypeIdentifier>(0x5ba36127, 0x195feae1)</TypeIdentifier>
					<Name>Input signal</Name>
				</Input>
			</Inputs>
			<Outputs>
				<Output>
					<TypeIdentifier>(0x5ba36127, 0x195feae1)</TypeIdentifier>
					<Name>Filtered signal</Name>
				</Output>
			</Outputs>
			<Settings>
				<Setting>
					<TypeIdentifier>(0x2f2c606c, 0x8512ed68)</TypeIdentifier>
					<Name>Filter method</Name>
					<DefaultValue>Butterworth</DefaultValue>
					<Value>Butterworth</Value>
					<Modifiability>false</Modifiability>
				</Setting>
				<Setting>
					<TypeIdentifier>(0xfa20178e, 0x4cba62e9)</TypeIdentifier>
					<Name>Filter type</Name>
					<DefaultValue>Low pass</DefaultValue>
					<Value>Band pass</Value>
					<Modifiability>false</Modifiability>
				</Setting>
				<Setting>
					<TypeIdentifier>(0x007deef9, 0x2f3e95c6)</TypeIdentifier>
					<Name>Filter order</Name>
					<DefaultValue>4</DefaultValue>
					<Value>4</Value>
					<Modifiability>false</Modifiability>
				</Setting>
				<Setting>
					<TypeIdentifier>(0x512a166f, 0x5c3ef83f)</TypeIdentifier>
					<Name>Low cut frequency (Hz)</Name>
					<DefaultValue>29</DefaultValue>
					<Value>1.000000</Value>
					<Modifiability>false</Modifiability>
				</Setting>
				<Setting>
					<TypeIdentifier>(0x512a166f, 0x5c3ef83f)</TypeIdentifier>
					<Name>High cut frequency (Hz)</Name>
					<DefaultValue>40</DefaultValue>
					<Value>15</Value>
					<Modifiability>false</Modifiability>
				</Setting>
				<Setting>
					<TypeIdentifier>(0x512a166f, 0x5c3ef83f)</TypeIdentifier>
					<Name>Pass band ripple (dB)</Name>
					<DefaultValue>0.5</DefaultValue>
					<Value>0.500000</Value>
					<Modifiability>false</Modifiability>
				</Setting>
			</Settings>
			<Attributes>
				<Attribute>
					<Identifier>(0x1fa7a38f, 0x54edbe0b)</Identifier>
					<Value>-464.000000</Value>
				</Attribute>
				<Attribute>
					<Identifier>(0x1fa963f5, 0x1a638cd4)</Identifier>
					<Value>48</Value>
				</Attribute>
				<Attribute>
					<Identifier>(0x207c9054, 0x3c841b63)</Identifier>
					<Value>201.000000</Value>
				</Attribute>
				<Attribute>
					<Identifier>(0x4e7b798a, 0x183beafb)</Identifier>
					<Value>(0x27a4ceec, 0x876d6384)</Value>
				</Attribute>
				<Attribute>
					<Identifier>(0xac367a9c, 0x2da95abe)</Identifier>
					<Value>39</Value>
				</Attribute>
				<Attribute>
					<Identifier>(0xad100179, 0xa3c984ab)</Identifier>
					<Value>161</Value>
				</Attribute>
			</Attributes>
		</Box>
		<Box>
			<Identifier>(0x2d881383, 0x0b1b10f5)</Identifier>
			<Name>Channel Selector</Name>
			<AlgorithmClassIdentifier>(0x361722e8, 0x311574e8)</AlgorithmClassIdentifier>
			<Inputs>
				<Input>
					<TypeIdentifier>(0x5ba36127, 0x195feae1)</TypeIdentifier>
					<Name>Input signal</Name>
				</Input>
			</Inputs>
			<Outputs>
				<Output>
					<TypeIdentifier>(0x5ba36127, 0x195feae1)</TypeIdentifier>
					<Name>Output signal</Name>
				</Output>
			</Outputs>
			<Settings>
				<Setting>
					<TypeIdentifier>(0x79a9edeb, 0x245d83fc)</TypeIdentifier>
					<Name>Channel List</Name>
					<DefaultValue>:</DefaultValue>
					<Value>${externalP300_Channels}</Value>
					<Modifiability>false</Modifiability>
				</Setting>
				<Setting>
					<TypeIdentifier>(0x3bcf9e67, 0x0c23994d)</TypeIdentifier>
					<Name>Action</Name>
					<DefaultValue>Select</DefaultValue>
					<Value>Select</Value>
					<Modifiability>false</Modifiability>
				</Setting>
				<Setting>
					<TypeIdentifier>(0x666f25e9, 0x3e5738d6)</TypeIdentifier>
					<Name>Channel Matching Method</Name>
					<DefaultValue>Smart</DefaultValue>
					<Value>Name</Value>
					<Modifiability>false</Modifiability>
				</Setting>
			</Settings>
			<Attributes>
				<Attribute>
					<Identifier>(0x1fa7a38f, 0x54edbe0b)</Identifier>
					<Value>-544.000000</Value>
				</Attribute>
				<Attribute>
					<Identifier>(0x1fa963f5, 0x1a638cd4)</Identifier>
					<Value>48</Value>
				</Attribute>
				<Attribute>
					<Identifier>(0x207c9054, 0x3c841b63)</Identifier>
					<Value>176.000000</Value>
				</Attribute>
				<Attribute>
					<Identifier>(0x30a4e5c9, 0x83502953)</Identifier>
					<Value></Value>
				</Attribute>
				<Attribute>
					<Identifier>(0x4e7b798a, 0x183beafb)</Identifier>
					<Value>(0x95781be1, 0xa38dce2d)</Value>
				</Attribute>
				<Attribute>
					<Identifier>(0x527ad68d, 0x16d746a0)</Identifier>
					<Value></Value>
				</Attribute>
				<Attribute>
					<Identifier>(0xad100179, 0xa3c984ab)</Identifier>
					<Value>132</Value>
				</Attribute>
				<Attribute>
					<Identifier>(0xc73e83ec, 0xf855c5bc)</Identifier>
					<Value>false</Value>
				</Attribute>
				<Attribute>
					<Identifier>(0xc80ce8af, 0xf699f813)</Identifier>
					<Value>1</Value>
				</Attribute>
				<Attribute>
					<Identifier>(0xce18836a, 0x9c0eb403)</Identifier>
					<Value>3</Value>
				</Attribute>
				<Attribute>
					<Identifier>(0xcfad85b0, 0x7c6d841c)</Identifier>
					<Value>1</Value>
				</Attribute>
			</Attributes>
		</Box>
		<Box>
			<Identifier>(0x31badaf7, 0x53b152b4)</Identifier>
			<Name>Epoch variance</Name>
			<AlgorithmClassIdentifier>(0x335384ea, 0x88c917d9)</AlgorithmClassIdentifier>
			<Inputs>
				<Input>
					<TypeIdentifier>(0x544a003e, 0x6dcba5f6)</TypeIdentifier>
					<Name>Input epochs</Name>
				</Input>
			</Inputs>
			<Outputs>
				<Output>
					<TypeIdentifier>(0x544a003e, 0x6dcba5f6)</TypeIdentifier>
					<Name>Averaged epochs</Name>
				</Output>
				<Output>
					<TypeIdentifier>(0x544a003e, 0x6dcba5f6)</TypeIdentifier>
					<Name>Variance of epochs</Name>
				</Output>
				<Output>
					<TypeIdentifier>(0x544a003e, 0x6dcba5f6)</TypeIdentifier>
					<Name>Confidence bounds</Name>
				</Output>
			</Outputs>
			<Settings>
				<Setting>
					<TypeIdentifier>(0x6530bdb1, 0xd057bbfe)</TypeIdentifier>
					<Name>Averaging type</Name>
					<DefaultValue>Moving epoch average</DefaultValue>
					<Value>Cumulative average</Value>
					<Modifiability>false</Modifiability>
				</Setting>
				<Setting>
					<TypeIdentifier>(0x007deef9, 0x2f3e95c6)</TypeIdentifier>
					<Name>Epoch count</Name>
					<DefaultValue>4</DefaultValue>
					<Value>4</Value>
					<Modifiability>false</Modifiability>
				</Setting>
				<Setting>
					<TypeIdentifier>(0x512a166f, 0x5c3ef83f)</TypeIdentifier>
					<Name>Significance level</Name>
					<DefaultValue>0.01</DefaultValue>
					<Value>0.05</Value>
					<Modifiability>false</Modifiability>
				</Setting>
			</Settings>
			<Attributes>
				<Attribute>
					<Identifier>(0x1fa7a38f, 0x54edbe0b)</Identifier>
					<Value>-128.000000</Value>
				</Attribute>
				<Attribute>
					<Identifier>(0x1fa963f5, 0x1a638cd4)</Identifier>
					<Value>48</Value>
				</Attribute>
				<Attribute>
					<Identifier>(0x207c9054, 0x3c841b63)</Identifier>
					<Value>288.000000</Value>
				</Attribute>
				<Attribute>
					<Identifier>(0x4e7b798a, 0x183beafb)</Identifier>
					<Value>(0xe7fb819b, 0x3ff4203d)</Value>
				</Attribute>
				<Attribute>
					<Identifier>(0x527ad68d, 0x16d746a0)</Identifier>
					<Value></Value>
				</Attribute>
				<Attribute>
					<Identifier>(0xad100179, 0xa3c984ab)</Identifier>
					<Value>117</Value>
				</Attribute>
				<Attribute>
					<Identifier>(0xc73e83ec, 0xf855c5bc)</Identifier>
					<Value>false</Value>
				</Attribute>
				<Attribute>
					<Identifier>(0xc80ce8af, 0xf699f813)</Identifier>
					<Value>3</Value>
				</Attribute>
				<Attribute>
					<Identifier>(0xce18836a, 0x9c0eb403)</Identifier>
					<Value>3</Value>
				</Attribute>
				<Attribute>
					<Identifier>(0xcfad85b0, 0x7c6d841c)</Identifier>
					<Value>1</Value>
				</Attribute>
			</Attributes>
		</Box>
		<Box>
			<Identifier>(0x370dd47f, 0x1d81283a)</Identifier>
			<Name>Stimulation based epoching</Name>
			<AlgorithmClassIdentifier>(0x426163d1, 0x324237b0)</AlgorithmClassIdentifier>
			<Inputs>
				<Input>
					<TypeIdentifier>(0x5ba36127, 0x195feae1)</TypeIdentifier>
					<Name>Input signal</Name>
				</Input>
				<Input>
					<TypeIdentifier>(0x6f752dd0, 0x082a321e)</TypeIdentifier>
					<Name>Input stimulations</Name>
				</Input>
			</Inputs>
			<Outputs>
				<Output>
					<TypeIdentifier>(0x5ba36127, 0x195feae1)</TypeIdentifier>
					<Name>Epoched signal</Name>
				</Output>
				<Output>
					<TypeIdentifier>(0x6f752dd0, 0x082a321e)</TypeIdentifier>
					<Name>Resynced stimulations</Name>
				</Output>
			</Outputs>
			<Settings>
				<Setting>
					<TypeIdentifier>(0x512a166f, 0x5c3ef83f)</TypeIdentifier>
					<Name>Epoch duration (in sec)</Name>
					<DefaultValue>1</DefaultValue>
					<Value>0.6</Value>
					<Modifiability>false</Modifiability>
				</Setting>
				<Setting>
					<TypeIdentifier>(0x512a166f, 0x5c3ef83f)</TypeIdentifier>
					<Name>Epoch offset (in sec)</Name>
					<DefaultValue>0.5</DefaultValue>
					<Value>0</Value>
					<Modifiability>false</Modifiability>
				</Setting>
				<Setting>
					<TypeIdentifier>(0x2c132d6e, 0x44ab0d97)</TypeIdentifier>
					<Name>Stimulation to epoch from</Name>
					<DefaultValue>OVTK_GDF_VEP</DefaultValue>
					<Value>192</Value>
					<Modifiability>false</Modifiability>
				</Setting>
			</Settings>
			<Attributes>
				<Attribute>
					<Identifier>(0x1fa7a38f, 0x54edbe0b)</Identifier>
					<Value>-224</Value>
				</Attribute>
				<Attribute>
					<Identifier>(0x1fa963f5, 0x1a638cd4)</Identifier>
					<Value>31</Value>
				</Attribute>
				<Attribute>
					<Identifier>(0x207c9054, 0x3c841b63)</Identifier>
					<Value>336</Value>
				</Attribute>
				<Attribute>
					<Identifier>(0x4e7b798a, 0x183beafb)</Identifier>
					<Value>(0x95ec5f7e, 0x885aeb68)</Value>
				</Attribute>
				<Attribute>
					<Identifier>(0xad100179, 0xa3c984ab)</Identifier>
					<Value>208</Value>
				</Attribute>
				<Attribute>
					<Identifier>(0xc80ce8af, 0xf699f813)</Identifier>
					<Value>2</Value>
				</Attribute>
				<Attribute>
					<Identifier>(0xce18836a, 0x9c0eb403)</Identifier>
					<Value>3</Value>
				</Attribute>
				<Attribute>
					<Identifier>(0xcfad85b0, 0x7c6d841c)</Identifier>
					<Value>2</Value>
				</Attribute>
			</Attributes>
		</Box>
		<Box>
			<Identifier>(0x395ae00b, 0x368db921)</Identifier>
			<Name>Signal Decimation</Name>
			<AlgorithmClassIdentifier>(0x012f4bea, 0x3be37c66)</AlgorithmClassIdentifier>
			<Inputs>
				<Input>
					<TypeIdentifier>(0x5ba36127, 0x195feae1)</TypeIdentifier>
					<Name>Input signal</Name>
				</Input>
			</Inputs>
			<Outputs>
				<Output>
					<TypeIdentifier>(0x5ba36127, 0x195feae1)</TypeIdentifier>
					<Name>Output signal</Name>
				</Output>
			</Outputs>
			<Settings>
				<Setting>
					<TypeIdentifier>(0x007deef9, 0x2f3e95c6)</TypeIdentifier>
					<Name>Decimation factor</Name>
					<DefaultValue>8</DefaultValue>
					<Value>4</Value>
					<Modifiability>false</Modifiability>
				</Setting>
			</Settings>
			<Attributes>
				<Attribute>
					<Identifier>(0x1fa7a38f, 0x54edbe0b)</Identifier>
					<Value>-400</Value>
				</Attribute>
				<Attribute>
					<Identifier>(0x1fa963f5, 0x1a638cd4)</Identifier>
					<Value>31</Value>
				</Attribute>
				<Attribute>
					<Identifier>(0x207c9054, 0x3c841b63)</Identifier>
					<Value>192</Value>
				</Attribute>
				<Attribute>
					<Identifier>(0x4e7b798a, 0x183beafb)</Identifier>
					<Value>(0x5082af41, 0xd0fbf4cb)</Value>
				</Attribute>
				<Attribute>
					<Identifier>(0xad100179, 0xa3c984ab)</Identifier>
					<Value>139</Value>
				</Attribute>
				<Attribute>
					<Identifier>(0xc80ce8af, 0xf699f813)</Identifier>
					<Value>1</Value>
				</Attribute>
				<Attribute>
					<Identifier>(0xce18836a, 0x9c0eb403)</Identifier>
					<Value>1</Value>
				</Attribute>
				<Attribute>
					<Identifier>(0xcfad85b0, 0x7c6d841c)</Identifier>
					<Value>1</Value>
				</Attribute>
			</Attributes>
		</Box>
		<Box>
			<Identifier>(0x427f2e34, 0x6ad58c36)</Identifier>
			<Name>ERP plot</Name>
			<AlgorithmClassIdentifier>(0x10dc6917, 0x2b29b2a0)</AlgorithmClassIdentifier>
			<Inputs>
				<Input>
					<TypeIdentifier>(0x6f752dd0, 0x082a321e)</TypeIdentifier>
					<Name>Trigger</Name>
				</Input>
				<Input>
					<TypeIdentifier>(0x544a003e, 0x6dcba5f6)</TypeIdentifier>
					<Name>ERP1</Name>
				</Input>
				<Input>
					<TypeIdentifier>(0x544a003e, 0x6dcba5f6)</TypeIdentifier>
					<Name>Variance1</Name>
				</Input>
				<Input>
					<TypeIdentifier>(0x544a003e, 0x6dcba5f6)</TypeIdentifier>
					<Name>ERP2</Name>
				</Input>
				<Input>
					<TypeIdentifier>(0x544a003e, 0x6dcba5f6)</TypeIdentifier>
					<Name>Variance2</Name>
				</Input>
			</Inputs>
			<Settings>
				<Setting>
					<TypeIdentifier>(0x330306dd, 0x74a95f98)</TypeIdentifier>
					<Name>Filename final figure</Name>
					<DefaultValue></DefaultValue>
					<Value>${Path_Data}/scenarios/signals/${externalP300_SubjectName}/p300_${SubjectName}_$core{date}_$core{time}.png</Value>
					<Modifiability>false</Modifiability>
				</Setting>
				<Setting>
					<TypeIdentifier>(0x2c132d6e, 0x44ab0d97)</TypeIdentifier>
					<Name>Trigger to save figure</Name>
					<DefaultValue>OVTK_StimulationId_ExperimentStop</DefaultValue>
					<Value>182</Value>
					<Modifiability>false</Modifiability>
				</Setting>
				<Setting>
					<TypeIdentifier>(0x7f45a2a9, 0x7db12219)</TypeIdentifier>
					<Name>Line color 1</Name>
					<DefaultValue>0,0,0</DefaultValue>
					<Value>15,81,13</Value>
					<Modifiability>false</Modifiability>
				</Setting>
				<Setting>
					<TypeIdentifier>(0x79a9edeb, 0x245d83fc)</TypeIdentifier>
					<Name>Line label 1</Name>
					<DefaultValue>curve 1</DefaultValue>
					<Value>target</Value>
					<Modifiability>false</Modifiability>
				</Setting>
				<Setting>
					<TypeIdentifier>(0x7f45a2a9, 0x7db12219)</TypeIdentifier>
					<Name>Line color 2</Name>
					<DefaultValue>0,0,0</DefaultValue>
					<Value>87,14,14</Value>
					<Modifiability>false</Modifiability>
				</Setting>
				<Setting>
					<TypeIdentifier>(0x79a9edeb, 0x245d83fc)</TypeIdentifier>
					<Name>Line label 2</Name>
					<DefaultValue>curve</DefaultValue>
					<Value>non-target</Value>
					<Modifiability>false</Modifiability>
				</Setting>
			</Settings>
			<Attributes>
				<Attribute>
					<Identifier>(0x1fa7a38f, 0x54edbe0b)</Identifier>
					<Value>-32</Value>
				</Attribute>
				<Attribute>
					<Identifier>(0x1fa963f5, 0x1a638cd4)</Identifier>
					<Value>48</Value>
				</Attribute>
				<Attribute>
					<Identifier>(0x207c9054, 0x3c841b63)</Identifier>
					<Value>160</Value>
				</Attribute>
				<Attribute>
					<Identifier>(0x4e7b798a, 0x183beafb)</Identifier>
					<Value>(0x6426093c, 0x90aed000)</Value>
				</Attribute>
				<Attribute>
					<Identifier>(0xad100179, 0xa3c984ab)</Identifier>
					<Value>71</Value>
				</Attribute>
				<Attribute>
					<Identifier>(0xce18836a, 0x9c0eb403)</Identifier>
					<Value>3</Value>
				</Attribute>
				<Attribute>
					<Identifier>(0xcfad85b0, 0x7c6d841c)</Identifier>
					<Value>1</Value>
				</Attribute>
			</Attributes>
		</Box>
		<Box>
			<Identifier>(0x448f38d0, 0x7c5a437c)</Identifier>
			<Name>Epoch variance</Name>
			<AlgorithmClassIdentifier>(0x335384ea, 0x88c917d9)</AlgorithmClassIdentifier>
			<Inputs>
				<Input>
					<TypeIdentifier>(0x544a003e, 0x6dcba5f6)</TypeIdentifier>
					<Name>Input epochs</Name>
				</Input>
			</Inputs>
			<Outputs>
				<Output>
					<TypeIdentifier>(0x544a003e, 0x6dcba5f6)</TypeIdentifier>
					<Name>Averaged epochs</Name>
				</Output>
				<Output>
					<TypeIdentifier>(0x544a003e, 0x6dcba5f6)</TypeIdentifier>
					<Name>Variance of epochs</Name>
				</Output>
				<Output>
					<TypeIdentifier>(0x544a003e, 0x6dcba5f6)</TypeIdentifier>
					<Name>Confidence bounds</Name>
				</Output>
			</Outputs>
			<Settings>
				<Setting>
					<TypeIdentifier>(0x6530bdb1, 0xd057bbfe)</TypeIdentifier>
					<Name>Averaging type</Name>
					<DefaultValue>Moving epoch average</DefaultValue>
					<Value>Cumulative average</Value>
					<Modifiability>false</Modifiability>
				</Setting>
				<Setting>
					<TypeIdentifier>(0x007deef9, 0x2f3e95c6)</TypeIdentifier>
					<Name>Epoch count</Name>
					<DefaultValue>4</DefaultValue>
					<Value>4</Value>
					<Modifiability>false</Modifiability>
				</Setting>
				<Setting>
					<TypeIdentifier>(0x512a166f, 0x5c3ef83f)</TypeIdentifier>
					<Name>Significance level</Name>
					<DefaultValue>0.01</DefaultValue>
					<Value>0.05</Value>
					<Modifiability>false</Modifiability>
				</Setting>
			</Settings>
			<Attributes>
				<Attribute>
					<Identifier>(0x1fa7a38f, 0x54edbe0b)</Identifier>
					<Value>-128.000000</Value>
				</Attribute>
				<Attribute>
					<Identifier>(0x1fa963f5, 0x1a638cd4)</Identifier>
					<Value>48</Value>
				</Attribute>
				<Attribute>
					<Identifier>(0x207c9054, 0x3c841b63)</Identifier>
					<Value>32.000000</Value>
				</Attribute>
				<Attribute>
					<Identifier>(0x4e7b798a, 0x183beafb)</Identifier>
					<Value>(0xe7fb819b, 0x3ff4203d)</Value>
				</Attribute>
				<Attribute>
					<Identifier>(0x527ad68d, 0x16d746a0)</Identifier>
					<Value></Value>
				</Attribute>
				<Attribute>
					<Identifier>(0xad100179, 0xa3c984ab)</Identifier>
					<Value>117</Value>
				</Attribute>
				<Attribute>
					<Identifier>(0xc73e83ec, 0xf855c5bc)</Identifier>
					<Value>false</Value>
				</Attribute>
				<Attribute>
					<Identifier>(0xc80ce8af, 0xf699f813)</Identifier>
					<Value>3</Value>
				</Attribute>
				<Attribute>
					<Identifier>(0xce18836a, 0x9c0eb403)</Identifier>
					<Value>3</Value>
				</Attribute>
				<Attribute>
					<Identifier>(0xcfad85b0, 0x7c6d841c)</Identifier>
					<Value>1</Value>
				</Attribute>
			</Attributes>
		</Box>
		<Box>
			<Identifier>(0x50b18f5e, 0x0f444378)</Identifier>
			<Name>Stimulation based epoching</Name>
			<AlgorithmClassIdentifier>(0x426163d1, 0x324237b0)</AlgorithmClassIdentifier>
			<Inputs>
				<Input>
					<TypeIdentifier>(0x5ba36127, 0x195feae1)</TypeIdentifier>
					<Name>Input signal</Name>
				</Input>
				<Input>
					<TypeIdentifier>(0x6f752dd0, 0x082a321e)</TypeIdentifier>
					<Name>Input stimulations</Name>
				</Input>
			</Inputs>
			<Outputs>
				<Output>
					<TypeIdentifier>(0x5ba36127, 0x195feae1)</TypeIdentifier>
					<Name>Epoched signal</Name>
				</Output>
				<Output>
					<TypeIdentifier>(0x6f752dd0, 0x082a321e)</TypeIdentifier>
					<Name>Resynced stimulations</Name>
				</Output>
			</Outputs>
			<Settings>
				<Setting>
					<TypeIdentifier>(0x512a166f, 0x5c3ef83f)</TypeIdentifier>
					<Name>Epoch duration (in sec)</Name>
					<DefaultValue>1</DefaultValue>
					<Value>0.6</Value>
					<Modifiability>false</Modifiability>
				</Setting>
				<Setting>
					<TypeIdentifier>(0x512a166f, 0x5c3ef83f)</TypeIdentifier>
					<Name>Epoch offset (in sec)</Name>
					<DefaultValue>0.5</DefaultValue>
					<Value>0</Value>
					<Modifiability>false</Modifiability>
				</Setting>
				<Setting>
					<TypeIdentifier>(0x2c132d6e, 0x44ab0d97)</TypeIdentifier>
					<Name>Stimulation to epoch from</Name>
					<DefaultValue>OVTK_GDF_VEP</DefaultValue>
					<Value>191</Value>
					<Modifiability>false</Modifiability>
				</Setting>
			</Settings>
			<Attributes>
				<Attribute>
					<Identifier>(0x1fa7a38f, 0x54edbe0b)</Identifier>
					<Value>-224</Value>
				</Attribute>
				<Attribute>
					<Identifier>(0x1fa963f5, 0x1a638cd4)</Identifier>
					<Value>31</Value>
				</Attribute>
				<Attribute>
					<Identifier>(0x207c9054, 0x3c841b63)</Identifier>
					<Value>48</Value>
				</Attribute>
				<Attribute>
					<Identifier>(0x4e7b798a, 0x183beafb)</Identifier>
					<Value>(0x95ec5f7e, 0x885aeb68)</Value>
				</Attribute>
				<Attribute>
					<Identifier>(0xad100179, 0xa3c984ab)</Identifier>
					<Value>208</Value>
				</Attribute>
				<Attribute>
					<Identifier>(0xc80ce8af, 0xf699f813)</Identifier>
					<Value>2</Value>
				</Attribute>
				<Attribute>
					<Identifier>(0xce18836a, 0x9c0eb403)</Identifier>
					<Value>3</Value>
				</Attribute>
				<Attribute>
					<Identifier>(0xcfad85b0, 0x7c6d841c)</Identifier>
					<Value>2</Value>
				</Attribute>
			</Attributes>
		</Box>
		<Box>
			<Identifier>(0x720827bf, 0x0c9d02c9)</Identifier>
			<Name>Keyboard stimulator</Name>
			<AlgorithmClassIdentifier>(0x00d317b9, 0x6324c3ff)</AlgorithmClassIdentifier>
			<Outputs>
				<Output>
					<TypeIdentifier>(0x6f752dd0, 0x082a321e)</TypeIdentifier>
					<Name>Outgoing Stimulations</Name>
				</Output>
			</Outputs>
			<Settings>
				<Setting>
					<TypeIdentifier>(0x330306dd, 0x74a95f98)</TypeIdentifier>
					<Name>Filename</Name>
					<DefaultValue>../share/openvibe-plugins/stimulation/simple-keyboard-to-stimulations.txt</DefaultValue>
					<Value>${Player_ScenarioDirectory}/simple-keyboard-to-stimulations.txt</Value>
					<Modifiability>false</Modifiability>
				</Setting>
			</Settings>
			<Attributes>
				<Attribute>
					<Identifier>(0x1fa7a38f, 0x54edbe0b)</Identifier>
					<Value>-528</Value>
				</Attribute>
				<Attribute>
					<Identifier>(0x1fa963f5, 0x1a638cd4)</Identifier>
					<Value>31</Value>
				</Attribute>
				<Attribute>
					<Identifier>(0x207c9054, 0x3c841b63)</Identifier>
					<Value>720</Value>
				</Attribute>
				<Attribute>
					<Identifier>(0x4e7b798a, 0x183beafb)</Identifier>
					<Value>(0x8d89d3b7, 0x8339d210)</Value>
				</Attribute>
				<Attribute>
					<Identifier>(0xad100179, 0xa3c984ab)</Identifier>
					<Value>155</Value>
				</Attribute>
				<Attribute>
					<Identifier>(0xc67a01dc, 0x28ce06c1)</Identifier>
					<Value></Value>
				</Attribute>
				<Attribute>
					<Identifier>(0xc80ce8af, 0xf699f813)</Identifier>
					<Value>1</Value>
				</Attribute>
				<Attribute>
					<Identifier>(0xce18836a, 0x9c0eb403)</Identifier>
					<Value>1</Value>
				</Attribute>
			</Attributes>
		</Box>
	</Boxes>
	<Links>
		<Link>
			<Identifier>(0x09180503, 0x451c0df6)</Identifier>
			<Source>
				<BoxIdentifier>(0x081fe9aa, 0x731358b8)</BoxIdentifier>
				<BoxOutputIndex>2</BoxOutputIndex>
			</Source>
			<Target>
				<BoxIdentifier>(0x370dd47f, 0x1d81283a)</BoxIdentifier>
				<BoxInputIndex>1</BoxInputIndex>
			</Target>
			<Attributes>
				<Attribute>
					<Identifier>(0x1b32c44c, 0x1905e0e9)</Identifier>
					<Value>-594</Value>
				</Attribute>
				<Attribute>
					<Identifier>(0x358ae8b5, 0x0f8bacd1)</Identifier>
					<Value>207</Value>
				</Attribute>
				<Attribute>
					<Identifier>(0x3f0a3b27, 0x570913d2)</Identifier>
					<Value>-244</Value>
				</Attribute>
				<Attribute>
					<Identifier>(0x6267b5c5, 0x676e3e42)</Identifier>
					<Value>343</Value>
				</Attribute>
			</Attributes>
		</Link>
		<Link>
			<Identifier>(0x0a40ae6c, 0x740ba16a)</Identifier>
			<Source>
				<BoxIdentifier>(0x2d881383, 0x0b1b10f5)</BoxIdentifier>
				<BoxOutputIndex>0</BoxOutputIndex>
			</Source>
			<Target>
				<BoxIdentifier>(0x283e849b, 0x6ccb375a)</BoxIdentifier>
				<BoxInputIndex>0</BoxInputIndex>
			</Target>
			<Attributes>
				<Attribute>
					<Identifier>(0x1b32c44c, 0x1905e0e9)</Identifier>
					<Value>-514</Value>
				</Attribute>
				<Attribute>
					<Identifier>(0x358ae8b5, 0x0f8bacd1)</Identifier>
					<Value>176</Value>
				</Attribute>
				<Attribute>
					<Identifier>(0x3f0a3b27, 0x570913d2)</Identifier>
					<Value>-493</Value>
				</Attribute>
				<Attribute>
					<Identifier>(0x6267b5c5, 0x676e3e42)</Identifier>
					<Value>201</Value>
				</Attribute>
			</Attributes>
		</Link>
		<Link>
			<Identifier>(0x142865f9, 0x205dba92)</Identifier>
			<Source>
				<BoxIdentifier>(0x31badaf7, 0x53b152b4)</BoxIdentifier>
				<BoxOutputIndex>0</BoxOutputIndex>
			</Source>
			<Target>
				<BoxIdentifier>(0x427f2e34, 0x6ad58c36)</BoxIdentifier>
				<BoxInputIndex>3</BoxInputIndex>
			</Target>
			<Attributes>
				<Attribute>
					<Identifier>(0x1b32c44c, 0x1905e0e9)</Identifier>
					<Value>-98</Value>
				</Attribute>
				<Attribute>
					<Identifier>(0x358ae8b5, 0x0f8bacd1)</Identifier>
					<Value>273</Value>
				</Attribute>
				<Attribute>
					<Identifier>(0x3f0a3b27, 0x570913d2)</Identifier>
					<Value>-61</Value>
				</Attribute>
				<Attribute>
					<Identifier>(0x6267b5c5, 0x676e3e42)</Identifier>
					<Value>175</Value>
				</Attribute>
			</Attributes>
		</Link>
		<Link>
			<Identifier>(0x21713263, 0x327f3309)</Identifier>
			<Source>
				<BoxIdentifier>(0x081fe9aa, 0x731358b8)</BoxIdentifier>
				<BoxOutputIndex>2</BoxOutputIndex>
			</Source>
			<Target>
				<BoxIdentifier>(0x427f2e34, 0x6ad58c36)</BoxIdentifier>
				<BoxInputIndex>0</BoxInputIndex>
			</Target>
			<Attributes>
				<Attribute>
					<Identifier>(0x1b32c44c, 0x1905e0e9)</Identifier>
					<Value>-594</Value>
				</Attribute>
				<Attribute>
					<Identifier>(0x358ae8b5, 0x0f8bacd1)</Identifier>
					<Value>207</Value>
				</Attribute>
				<Attribute>
					<Identifier>(0x3f0a3b27, 0x570913d2)</Identifier>
					<Value>-61</Value>
				</Attribute>
				<Attribute>
					<Identifier>(0x6267b5c5, 0x676e3e42)</Identifier>
					<Value>130</Value>
				</Attribute>
			</Attributes>
		</Link>
		<Link>
			<Identifier>(0x2ff19a2a, 0x30c526ac)</Identifier>
			<Source>
				<BoxIdentifier>(0x081fe9aa, 0x731358b8)</BoxIdentifier>
				<BoxOutputIndex>2</BoxOutputIndex>
			</Source>
			<Target>
				<BoxIdentifier>(0x50b18f5e, 0x0f444378)</BoxIdentifier>
				<BoxInputIndex>1</BoxInputIndex>
			</Target>
			<Attributes>
				<Attribute>
					<Identifier>(0x1b32c44c, 0x1905e0e9)</Identifier>
					<Value>-594</Value>
				</Attribute>
				<Attribute>
					<Identifier>(0x358ae8b5, 0x0f8bacd1)</Identifier>
					<Value>207</Value>
				</Attribute>
				<Attribute>
					<Identifier>(0x3f0a3b27, 0x570913d2)</Identifier>
					<Value>-244</Value>
				</Attribute>
				<Attribute>
					<Identifier>(0x6267b5c5, 0x676e3e42)</Identifier>
					<Value>55</Value>
				</Attribute>
			</Attributes>
		</Link>
		<Link>
			<Identifier>(0x3cfc244b, 0x79229524)</Identifier>
			<Source>
				<BoxIdentifier>(0x081fe9aa, 0x731358b8)</BoxIdentifier>
				<BoxOutputIndex>1</BoxOutputIndex>
			</Source>
			<Target>
				<BoxIdentifier>(0x2d881383, 0x0b1b10f5)</BoxIdentifier>
				<BoxInputIndex>0</BoxInputIndex>
			</Target>
			<Attributes>
				<Attribute>
					<Identifier>(0x1b32c44c, 0x1905e0e9)</Identifier>
					<Value>-594</Value>
				</Attribute>
				<Attribute>
					<Identifier>(0x358ae8b5, 0x0f8bacd1)</Identifier>
					<Value>192</Value>
				</Attribute>
				<Attribute>
					<Identifier>(0x3f0a3b27, 0x570913d2)</Identifier>
					<Value>-573</Value>
				</Attribute>
				<Attribute>
					<Identifier>(0x6267b5c5, 0x676e3e42)</Identifier>
					<Value>176</Value>
				</Attribute>
			</Attributes>
		</Link>
		<Link>
			<Identifier>(0x3cfdcce9, 0x03f00a2b)</Identifier>
			<Source>
				<BoxIdentifier>(0x448f38d0, 0x7c5a437c)</BoxIdentifier>
				<BoxOutputIndex>2</BoxOutputIndex>
			</Source>
			<Target>
				<BoxIdentifier>(0x427f2e34, 0x6ad58c36)</BoxIdentifier>
				<BoxInputIndex>2</BoxInputIndex>
			</Target>
			<Attributes>
				<Attribute>
					<Identifier>(0x1b32c44c, 0x1905e0e9)</Identifier>
					<Value>-98</Value>
				</Attribute>
				<Attribute>
					<Identifier>(0x358ae8b5, 0x0f8bacd1)</Identifier>
					<Value>47</Value>
				</Attribute>
				<Attribute>
					<Identifier>(0x3f0a3b27, 0x570913d2)</Identifier>
					<Value>-61</Value>
				</Attribute>
				<Attribute>
					<Identifier>(0x6267b5c5, 0x676e3e42)</Identifier>
					<Value>160</Value>
				</Attribute>
			</Attributes>
		</Link>
		<Link>
			<Identifier>(0x3d9a43fc, 0x69bbac4e)</Identifier>
			<Source>
				<BoxIdentifier>(0x1c9d2a5e, 0x10945cc3)</BoxIdentifier>
				<BoxOutputIndex>0</BoxOutputIndex>
			</Source>
			<Target>
				<BoxIdentifier>(0x50b18f5e, 0x0f444378)</BoxIdentifier>
				<BoxInputIndex>0</BoxInputIndex>
			</Target>
			<Attributes>
				<Attribute>
					<Identifier>(0x1b32c44c, 0x1905e0e9)</Identifier>
					<Value>-297</Value>
				</Attribute>
				<Attribute>
					<Identifier>(0x358ae8b5, 0x0f8bacd1)</Identifier>
					<Value>192</Value>
				</Attribute>
				<Attribute>
					<Identifier>(0x3f0a3b27, 0x570913d2)</Identifier>
					<Value>-244</Value>
				</Attribute>
				<Attribute>
					<Identifier>(0x6267b5c5, 0x676e3e42)</Identifier>
					<Value>40</Value>
				</Attribute>
			</Attributes>
		</Link>
		<Link>
			<Identifier>(0x3ee6af33, 0x0a81150f)</Identifier>
			<Source>
				<BoxIdentifier>(0x395ae00b, 0x368db921)</BoxIdentifier>
				<BoxOutputIndex>0</BoxOutputIndex>
			</Source>
			<Target>
				<BoxIdentifier>(0x1c9d2a5e, 0x10945cc3)</BoxIdentifier>
				<BoxInputIndex>0</BoxInputIndex>
			</Target>
			<Attributes>
				<Attribute>
					<Identifier>(0x1b32c44c, 0x1905e0e9)</Identifier>
					<Value>-378</Value>
				</Attribute>
				<Attribute>
					<Identifier>(0x358ae8b5, 0x0f8bacd1)</Identifier>
					<Value>192</Value>
				</Attribute>
				<Attribute>
					<Identifier>(0x3f0a3b27, 0x570913d2)</Identifier>
					<Value>-373</Value>
				</Attribute>
				<Attribute>
					<Identifier>(0x6267b5c5, 0x676e3e42)</Identifier>
					<Value>192</Value>
				</Attribute>
			</Attributes>
		</Link>
		<Link>
			<Identifier>(0x47f176b2, 0x694c7a37)</Identifier>
			<Source>
				<BoxIdentifier>(0x720827bf, 0x0c9d02c9)</BoxIdentifier>
				<BoxOutputIndex>0</BoxOutputIndex>
			</Source>
			<Target>
				<BoxIdentifier>(0x08e4d38b, 0x2814b4fc)</BoxIdentifier>
				<BoxInputIndex>0</BoxInputIndex>
			</Target>
			<Attributes>
				<Attribute>
					<Identifier>(0x1b32c44c, 0x1905e0e9)</Identifier>
					<Value>-506</Value>
				</Attribute>
				<Attribute>
					<Identifier>(0x358ae8b5, 0x0f8bacd1)</Identifier>
					<Value>720</Value>
				</Attribute>
				<Attribute>
					<Identifier>(0x3f0a3b27, 0x570913d2)</Identifier>
					<Value>-452</Value>
				</Attribute>
				<Attribute>
					<Identifier>(0x6267b5c5, 0x676e3e42)</Identifier>
					<Value>704</Value>
				</Attribute>
			</Attributes>
		</Link>
		<Link>
			<Identifier>(0x4aa0aa18, 0x2b72b96a)</Identifier>
			<Source>
				<BoxIdentifier>(0x448f38d0, 0x7c5a437c)</BoxIdentifier>
				<BoxOutputIndex>0</BoxOutputIndex>
			</Source>
			<Target>
				<BoxIdentifier>(0x427f2e34, 0x6ad58c36)</BoxIdentifier>
				<BoxInputIndex>1</BoxInputIndex>
			</Target>
			<Attributes>
				<Attribute>
					<Identifier>(0x1b32c44c, 0x1905e0e9)</Identifier>
					<Value>-98</Value>
				</Attribute>
				<Attribute>
					<Identifier>(0x358ae8b5, 0x0f8bacd1)</Identifier>
					<Value>17</Value>
				</Attribute>
				<Attribute>
					<Identifier>(0x3f0a3b27, 0x570913d2)</Identifier>
					<Value>-61</Value>
				</Attribute>
				<Attribute>
					<Identifier>(0x6267b5c5, 0x676e3e42)</Identifier>
					<Value>145</Value>
				</Attribute>
			</Attributes>
		</Link>
		<Link>
			<Identifier>(0x60d6d8c2, 0x4ef945e8)</Identifier>
			<Source>
				<BoxIdentifier>(0x283e849b, 0x6ccb375a)</BoxIdentifier>
				<BoxOutputIndex>0</BoxOutputIndex>
			</Source>
			<Target>
				<BoxIdentifier>(0x395ae00b, 0x368db921)</BoxIdentifier>
				<BoxInputIndex>0</BoxInputIndex>
			</Target>
			<Attributes>
				<Attribute>
					<Identifier>(0x1b32c44c, 0x1905e0e9)</Identifier>
					<Value>-434</Value>
				</Attribute>
				<Attribute>
					<Identifier>(0x358ae8b5, 0x0f8bacd1)</Identifier>
					<Value>201</Value>
				</Attribute>
				<Attribute>
					<Identifier>(0x3f0a3b27, 0x570913d2)</Identifier>
					<Value>-420</Value>
				</Attribute>
				<Attribute>
					<Identifier>(0x6267b5c5, 0x676e3e42)</Identifier>
					<Value>192</Value>
				</Attribute>
			</Attributes>
		</Link>
		<Link>
			<Identifier>(0x6752dfcb, 0x79ac51ab)</Identifier>
			<Source>
				<BoxIdentifier>(0x370dd47f, 0x1d81283a)</BoxIdentifier>
				<BoxOutputIndex>0</BoxOutputIndex>
			</Source>
			<Target>
				<BoxIdentifier>(0x31badaf7, 0x53b152b4)</BoxIdentifier>
				<BoxInputIndex>0</BoxInputIndex>
			</Target>
			<Attributes>
				<Attribute>
					<Identifier>(0x1b32c44c, 0x1905e0e9)</Identifier>
					<Value>-202</Value>
				</Attribute>
				<Attribute>
					<Identifier>(0x358ae8b5, 0x0f8bacd1)</Identifier>
					<Value>328</Value>
				</Attribute>
				<Attribute>
					<Identifier>(0x3f0a3b27, 0x570913d2)</Identifier>
					<Value>-157</Value>
				</Attribute>
				<Attribute>
					<Identifier>(0x6267b5c5, 0x676e3e42)</Identifier>
					<Value>288</Value>
				</Attribute>
			</Attributes>
		</Link>
		<Link>
			<Identifier>(0x6c35eddb, 0x4b973338)</Identifier>
			<Source>
				<BoxIdentifier>(0x50b18f5e, 0x0f444378)</BoxIdentifier>
				<BoxOutputIndex>0</BoxOutputIndex>
			</Source>
			<Target>
				<BoxIdentifier>(0x448f38d0, 0x7c5a437c)</BoxIdentifier>
				<BoxInputIndex>0</BoxInputIndex>
			</Target>
			<Attributes>
				<Attribute>
					<Identifier>(0x1b32c44c, 0x1905e0e9)</Identifier>
					<Value>-202</Value>
				</Attribute>
				<Attribute>
					<Identifier>(0x358ae8b5, 0x0f8bacd1)</Identifier>
					<Value>40</Value>
				</Attribute>
				<Attribute>
					<Identifier>(0x3f0a3b27, 0x570913d2)</Identifier>
					<Value>-157</Value>
				</Attribute>
				<Attribute>
					<Identifier>(0x6267b5c5, 0x676e3e42)</Identifier>
					<Value>32</Value>
				</Attribute>
			</Attributes>
		</Link>
		<Link>
			<Identifier>(0x7658af15, 0x47bf8a41)</Identifier>
			<Source>
				<BoxIdentifier>(0x31badaf7, 0x53b152b4)</BoxIdentifier>
				<BoxOutputIndex>2</BoxOutputIndex>
			</Source>
			<Target>
				<BoxIdentifier>(0x427f2e34, 0x6ad58c36)</BoxIdentifier>
				<BoxInputIndex>4</BoxInputIndex>
			</Target>
			<Attributes>
				<Attribute>
					<Identifier>(0x1b32c44c, 0x1905e0e9)</Identifier>
					<Value>-98</Value>
				</Attribute>
				<Attribute>
					<Identifier>(0x358ae8b5, 0x0f8bacd1)</Identifier>
					<Value>303</Value>
				</Attribute>
				<Attribute>
					<Identifier>(0x3f0a3b27, 0x570913d2)</Identifier>
					<Value>-61</Value>
				</Attribute>
				<Attribute>
					<Identifier>(0x6267b5c5, 0x676e3e42)</Identifier>
					<Value>190</Value>
				</Attribute>
			</Attributes>
		</Link>
		<Link>
			<Identifier>(0x770dfae2, 0x2fa26bbd)</Identifier>
			<Source>
				<BoxIdentifier>(0x1c9d2a5e, 0x10945cc3)</BoxIdentifier>
				<BoxOutputIndex>0</BoxOutputIndex>
			</Source>
			<Target>
				<BoxIdentifier>(0x370dd47f, 0x1d81283a)</BoxIdentifier>
				<BoxInputIndex>0</BoxInputIndex>
			</Target>
			<Attributes>
				<Attribute>
					<Identifier>(0x1b32c44c, 0x1905e0e9)</Identifier>
					<Value>-297</Value>
				</Attribute>
				<Attribute>
					<Identifier>(0x358ae8b5, 0x0f8bacd1)</Identifier>
					<Value>192</Value>
				</Attribute>
				<Attribute>
					<Identifier>(0x3f0a3b27, 0x570913d2)</Identifier>
					<Value>-244</Value>
				</Attribute>
				<Attribute>
					<Identifier>(0x6267b5c5, 0x676e3e42)</Identifier>
					<Value>328</Value>
				</Attribute>
			</Attributes>
		</Link>
	</Links>
	<MessageLinks></MessageLinks>
	<Comments></Comments>
	<VisualisationTree>
		<VisualisationWidget>
			<Identifier>(0x02a9ee6f, 0x3f0bd37a)</Identifier>
			<Type>3</Type>
			<ParentIdentifier>(0xffffffff, 0xffffffff)</ParentIdentifier>
			<BoxIdentifier>(0x50b18f5e, 0x0f444378)</BoxIdentifier>
			<NumChildren>0</NumChildren>
		</VisualisationWidget>
		<VisualisationWidget>
			<Identifier>(0x03738b72, 0x06f7e2c0)</Identifier>
			<Type>3</Type>
			<ParentIdentifier>(0xffffffff, 0xffffffff)</ParentIdentifier>
			<BoxIdentifier>(0x370dd47f, 0x1d81283a)</BoxIdentifier>
			<NumChildren>0</NumChildren>
		</VisualisationWidget>
		<VisualisationWidget>
			<Identifier>(0x0aa306b2, 0x1a27113c)</Identifier>
			<Type>3</Type>
			<ParentIdentifier>(0xffffffff, 0xffffffff)</ParentIdentifier>
			<BoxIdentifier>(0x283e849b, 0x6ccb375a)</BoxIdentifier>
			<NumChildren>0</NumChildren>
		</VisualisationWidget>
		<VisualisationWidget>
			<Identifier>(0x0ae7ecea, 0x56817d7b)</Identifier>
			<Type>3</Type>
			<ParentIdentifier>(0xffffffff, 0xffffffff)</ParentIdentifier>
			<BoxIdentifier>(0x395ae00b, 0x368db921)</BoxIdentifier>
			<NumChildren>0</NumChildren>
		</VisualisationWidget>
		<VisualisationWidget>
			<Identifier>(0x1fa502f5, 0x52947d64)</Identifier>
			<Type>3</Type>
			<ParentIdentifier>(0xffffffff, 0xffffffff)</ParentIdentifier>
			<BoxIdentifier>(0x081fe9aa, 0x731358b8)</BoxIdentifier>
			<NumChildren>0</NumChildren>
		</VisualisationWidget>
		<VisualisationWidget>
			<Identifier>(0x347cf9c5, 0x2c591f4e)</Identifier>
			<Name>Default window</Name>
			<Type>1</Type>
			<ParentIdentifier>(0xffffffff, 0xffffffff)</ParentIdentifier>
			<BoxIdentifier>(0xffffffff, 0xffffffff)</BoxIdentifier>
			<NumChildren>1</NumChildren>
			<Attributes>
				<Attribute>
					<Identifier>(0x4c90d4ad, 0x7a2554ec)</Identifier>
					<Value>320</Value>
				</Attribute>
				<Attribute>
					<Identifier>(0x7b814cca, 0x271df6dd)</Identifier>
					<Value>480</Value>
				</Attribute>
			</Attributes>
		</VisualisationWidget>
		<VisualisationWidget>
			<Identifier>(0x35f3ce77, 0x2519691c)</Identifier>
			<Type>3</Type>
			<ParentIdentifier>(0xffffffff, 0xffffffff)</ParentIdentifier>
			<BoxIdentifier>(0x720827bf, 0x0c9d02c9)</BoxIdentifier>
			<NumChildren>0</NumChildren>
		</VisualisationWidget>
		<VisualisationWidget>
			<Identifier>(0x4c40cf0e, 0x4071585c)</Identifier>
			<Type>3</Type>
			<ParentIdentifier>(0xffffffff, 0xffffffff)</ParentIdentifier>
			<BoxIdentifier>(0x427f2e34, 0x6ad58c36)</BoxIdentifier>
			<NumChildren>0</NumChildren>
		</VisualisationWidget>
		<VisualisationWidget>
			<Identifier>(0x681d44d1, 0x0987594b)</Identifier>
			<Type>3</Type>
			<ParentIdentifier>(0xffffffff, 0xffffffff)</ParentIdentifier>
			<BoxIdentifier>(0x1c9d2a5e, 0x10945cc3)</BoxIdentifier>
			<NumChildren>0</NumChildren>
		</VisualisationWidget>
		<VisualisationWidget>
			<Identifier>(0x6a357712, 0x6edfdc4a)</Identifier>
			<Type>3</Type>
			<ParentIdentifier>(0xffffffff, 0xffffffff)</ParentIdentifier>
			<BoxIdentifier>(0x08e4d38b, 0x2814b4fc)</BoxIdentifier>
			<NumChildren>0</NumChildren>
		</VisualisationWidget>
		<VisualisationWidget>
			<Identifier>(0x0900b083, 0x1553d287)</Identifier>
			<Name>Default tab</Name>
			<Type>2</Type>
			<ParentIdentifier>(0x347cf9c5, 0x2c591f4e)</ParentIdentifier>
			<Index>0</Index>
			<BoxIdentifier>(0xffffffff, 0xffffffff)</BoxIdentifier>
			<NumChildren>1</NumChildren>
		</VisualisationWidget>
		<VisualisationWidget>
			<Identifier>(0x7b526535, 0x469af47f)</Identifier>
			<Name>Empty</Name>
			<Type>0</Type>
			<ParentIdentifier>(0x0900b083, 0x1553d287)</ParentIdentifier>
			<Index>0</Index>
			<BoxIdentifier>(0xffffffff, 0xffffffff)</BoxIdentifier>
			<NumChildren>0</NumChildren>
		</VisualisationWidget>
	</VisualisationTree>
	<Attributes>
		<Attribute>
			<Identifier>(0x790d75b8, 0x3bb90c33)</Identifier>
			<Value></Value>
		</Attribute>
		<Attribute>
			<Identifier>(0x8c1fc55b, 0x7b433dc2)</Identifier>
			<Value>1.0</Value>
		</Attribute>
		<Attribute>
			<Identifier>(0x9f5c4075, 0x4a0d3666)</Identifier>
			<Value></Value>
		</Attribute>
		<Attribute>
			<Identifier>(0xf36a1567, 0xd13c53da)</Identifier>
			<Value>http://openvibe.inria.fr/p300-with-external-stimulator-tutorial/</Value>
		</Attribute>
		<Attribute>
			<Identifier>(0xf6b2e3fa, 0x7bd43926)</Identifier>
			<Value>p300-with-external-stimulator</Value>
		</Attribute>
		<Attribute>
			<Identifier>(0xf8034a49, 0x8b3f37cc)</Identifier>
			<Value>INRIA</Value>
		</Attribute>
	</Attributes>
</OpenViBE-Scenario>