<OpenViBE-Scenario>
	<Boxes>
		<Box>
			<Identifier>(0x0099cd55, 0x45b5fc65)</Identifier>
			<Name>Epoch variance</Name>
			<AlgorithmClassIdentifier>(0x335384ea, 0x88c917d9)</AlgorithmClassIdentifier>
			<Inputs>
				<Input>
					<TypeIdentifier>(0x544a003e, 0x6dcba5f6)</TypeIdentifier>
					<Name>Input epochs</Name>
				</Input>
			</Inputs>
			<Outputs>
				<Output>
					<TypeIdentifier>(0x544a003e, 0x6dcba5f6)</TypeIdentifier>
					<Name>Averaged epochs</Name>
				</Output>
				<Output>
					<TypeIdentifier>(0x544a003e, 0x6dcba5f6)</TypeIdentifier>
					<Name>Variance of epochs</Name>
				</Output>
				<Output>
					<TypeIdentifier>(0x544a003e, 0x6dcba5f6)</TypeIdentifier>
					<Name>Confidence bounds</Name>
				</Output>
			</Outputs>
			<Settings>
				<Setting>
					<TypeIdentifier>(0x6530bdb1, 0xd057bbfe)</TypeIdentifier>
					<Name>Averaging type</Name>
					<DefaultValue>Moving epoch average</DefaultValue>
					<Value>Cumulative average</Value>
					<Modifiability>false</Modifiability>
				</Setting>
				<Setting>
					<TypeIdentifier>(0x007deef9, 0x2f3e95c6)</TypeIdentifier>
					<Name>Epoch count</Name>
					<DefaultValue>4</DefaultValue>
					<Value>4</Value>
					<Modifiability>false</Modifiability>
				</Setting>
				<Setting>
					<TypeIdentifier>(0x512a166f, 0x5c3ef83f)</TypeIdentifier>
					<Name>Significance level</Name>
					<DefaultValue>0.01</DefaultValue>
					<Value>0.05</Value>
					<Modifiability>false</Modifiability>
				</Setting>
			</Settings>
			<Attributes>
				<Attribute>
					<Identifier>(0x1fa7a38f, 0x54edbe0b)</Identifier>
					<Value>-235.000000</Value>
				</Attribute>
				<Attribute>
					<Identifier>(0x1fa963f5, 0x1a638cd4)</Identifier>
					<Value>48</Value>
				</Attribute>
				<Attribute>
					<Identifier>(0x207c9054, 0x3c841b63)</Identifier>
					<Value>384.000000</Value>
				</Attribute>
				<Attribute>
					<Identifier>(0x4e7b798a, 0x183beafb)</Identifier>
					<Value>(0xe7fb819b, 0x3ff4203d)</Value>
				</Attribute>
				<Attribute>
					<Identifier>(0x527ad68d, 0x16d746a0)</Identifier>
					<Value></Value>
				</Attribute>
				<Attribute>
					<Identifier>(0xad100179, 0xa3c984ab)</Identifier>
					<Value>117</Value>
				</Attribute>
				<Attribute>
					<Identifier>(0xc73e83ec, 0xf855c5bc)</Identifier>
					<Value>false</Value>
				</Attribute>
				<Attribute>
					<Identifier>(0xc80ce8af, 0xf699f813)</Identifier>
					<Value>3</Value>
				</Attribute>
				<Attribute>
					<Identifier>(0xce18836a, 0x9c0eb403)</Identifier>
					<Value>3</Value>
				</Attribute>
				<Attribute>
					<Identifier>(0xcfad85b0, 0x7c6d841c)</Identifier>
					<Value>1</Value>
				</Attribute>
			</Attributes>
		</Box>
		<Box>
			<Identifier>(0x0752e564, 0x1aa4aa27)</Identifier>
			<Name>Stimulation Filter</Name>
			<AlgorithmClassIdentifier>(0x02f96101, 0x5e647cb8)</AlgorithmClassIdentifier>
			<Inputs>
				<Input>
					<TypeIdentifier>(0x6f752dd0, 0x082a321e)</TypeIdentifier>
					<Name>Stimulations</Name>
				</Input>
			</Inputs>
			<Outputs>
				<Output>
					<TypeIdentifier>(0x6f752dd0, 0x082a321e)</TypeIdentifier>
					<Name>Modified Stimulations</Name>
				</Output>
			</Outputs>
			<Settings>
				<Setting>
					<TypeIdentifier>(0x09e59e57, 0x8d4a553a)</TypeIdentifier>
					<Name>Default action</Name>
					<DefaultValue>Reject</DefaultValue>
					<Value>Reject</Value>
					<Modifiability>false</Modifiability>
				</Setting>
				<Setting>
					<TypeIdentifier>(0x512a166f, 0x5c3ef83f)</TypeIdentifier>
					<Name>Time range begin</Name>
					<DefaultValue>0</DefaultValue>
					<Value>0</Value>
					<Modifiability>false</Modifiability>
				</Setting>
				<Setting>
					<TypeIdentifier>(0x512a166f, 0x5c3ef83f)</TypeIdentifier>
					<Name>Time range end</Name>
					<DefaultValue>0</DefaultValue>
					<Value>0</Value>
					<Modifiability>false</Modifiability>
				</Setting>
				<Setting>
					<TypeIdentifier>(0x09e59e57, 0x8d4a553a)</TypeIdentifier>
					<Name>Action to perform</Name>
					<DefaultValue>Select</DefaultValue>
					<Value>Select</Value>
					<Modifiability>false</Modifiability>
				</Setting>
				<Setting>
					<TypeIdentifier>(0x2c132d6e, 0x44ab0d97)</TypeIdentifier>
					<Name>Stimulation range begin</Name>
					<DefaultValue>OVTK_StimulationId_Label_00</DefaultValue>
					<Value>183</Value>
					<Modifiability>false</Modifiability>
				</Setting>
				<Setting>
					<TypeIdentifier>(0x2c132d6e, 0x44ab0d97)</TypeIdentifier>
					<Name>Stimulation range end</Name>
					<DefaultValue>OVTK_StimulationId_Label_0F</DefaultValue>
					<Value>184</Value>
					<Modifiability>false</Modifiability>
				</Setting>
			</Settings>
			<Attributes>
				<Attribute>
					<Identifier>(0x1fa7a38f, 0x54edbe0b)</Identifier>
					<Value>-240</Value>
				</Attribute>
				<Attribute>
					<Identifier>(0x1fa963f5, 0x1a638cd4)</Identifier>
					<Value>48</Value>
				</Attribute>
				<Attribute>
					<Identifier>(0x207c9054, 0x3c841b63)</Identifier>
					<Value>-64</Value>
				</Attribute>
				<Attribute>
					<Identifier>(0x4e7b798a, 0x183beafb)</Identifier>
					<Value>(0x47859b3f, 0x1dfdf5cd)</Value>
				</Attribute>
				<Attribute>
					<Identifier>(0x61d11811, 0x71e65362)</Identifier>
					<Value></Value>
				</Attribute>
				<Attribute>
					<Identifier>(0xad100179, 0xa3c984ab)</Identifier>
					<Value>135</Value>
				</Attribute>
				<Attribute>
					<Identifier>(0xc80ce8af, 0xf699f813)</Identifier>
					<Value>1</Value>
				</Attribute>
				<Attribute>
					<Identifier>(0xce18836a, 0x9c0eb403)</Identifier>
					<Value>6</Value>
				</Attribute>
				<Attribute>
					<Identifier>(0xcfad85b0, 0x7c6d841c)</Identifier>
					<Value>1</Value>
				</Attribute>
			</Attributes>
		</Box>
		<Box>
			<Identifier>(0x079b4a02, 0x73098828)</Identifier>
			<Name>Player Controller</Name>
			<AlgorithmClassIdentifier>(0x5f426dce, 0x08456e13)</AlgorithmClassIdentifier>
			<Inputs>
				<Input>
					<TypeIdentifier>(0x6f752dd0, 0x082a321e)</TypeIdentifier>
					<Name>Stimulations</Name>
				</Input>
			</Inputs>
			<Settings>
				<Setting>
					<TypeIdentifier>(0x2c132d6e, 0x44ab0d97)</TypeIdentifier>
					<Name>Stimulation name</Name>
					<DefaultValue>OVTK_StimulationId_Label_00</DefaultValue>
					<Value>182</Value>
					<Modifiability>false</Modifiability>
				</Setting>
				<Setting>
					<TypeIdentifier>(0xcc14d8d6, 0xf27ecb73)</TypeIdentifier>
					<Name>Action to perform</Name>
					<DefaultValue>Pause</DefaultValue>
					<Value>Stop</Value>
					<Modifiability>false</Modifiability>
				</Setting>
			</Settings>
			<Attributes>
				<Attribute>
					<Identifier>(0x1fa7a38f, 0x54edbe0b)</Identifier>
					<Value>-128</Value>
				</Attribute>
				<Attribute>
					<Identifier>(0x1fa963f5, 0x1a638cd4)</Identifier>
					<Value>31</Value>
				</Attribute>
				<Attribute>
					<Identifier>(0x207c9054, 0x3c841b63)</Identifier>
					<Value>1232</Value>
				</Attribute>
				<Attribute>
					<Identifier>(0x4e7b798a, 0x183beafb)</Identifier>
					<Value>(0x568d148e, 0x650792b3)</Value>
				</Attribute>
				<Attribute>
					<Identifier>(0xad100179, 0xa3c984ab)</Identifier>
					<Value>131</Value>
				</Attribute>
				<Attribute>
					<Identifier>(0xce18836a, 0x9c0eb403)</Identifier>
					<Value>2</Value>
				</Attribute>
				<Attribute>
					<Identifier>(0xcfad85b0, 0x7c6d841c)</Identifier>
					<Value>1</Value>
				</Attribute>
			</Attributes>
		</Box>
		<Box>
			<Identifier>(0x10d954b5, 0x7150b4cf)</Identifier>
			<Name>Generic stream writer</Name>
			<AlgorithmClassIdentifier>(0x09c92218, 0x7c1216f8)</AlgorithmClassIdentifier>
			<Inputs>
				<Input>
					<TypeIdentifier>(0x403488e7, 0x565d70b6)</TypeIdentifier>
					<Name>Input stream 1</Name>
				</Input>
				<Input>
					<TypeIdentifier>(0x5ba36127, 0x195feae1)</TypeIdentifier>
					<Name>Input stream 2</Name>
				</Input>
				<Input>
					<TypeIdentifier>(0x6f752dd0, 0x082a321e)</TypeIdentifier>
					<Name>Input stream 3</Name>
				</Input>
			</Inputs>
			<Settings>
				<Setting>
					<TypeIdentifier>(0x330306dd, 0x74a95f98)</TypeIdentifier>
					<Name>Filename</Name>
					<DefaultValue>record-[$core{date}-$core{time}].ov</DefaultValue>
					<Value>${Player_ScenarioDirectory}/signals/${externalP300_SubjectName}/${externalP300_SubjectName}-${AcquisitionMode}-${SessionID}_$core{date}_$core{time}.ov</Value>
					<Modifiability>false</Modifiability>
				</Setting>
				<Setting>
					<TypeIdentifier>(0x2cdb2f0b, 0x12f231ea)</TypeIdentifier>
					<Name>Use compression</Name>
					<DefaultValue>true</DefaultValue>
					<Value>true</Value>
					<Modifiability>false</Modifiability>
				</Setting>
			</Settings>
			<Attributes>
				<Attribute>
					<Identifier>(0x1fa7a38f, 0x54edbe0b)</Identifier>
					<Value>-448</Value>
				</Attribute>
				<Attribute>
					<Identifier>(0x1fa963f5, 0x1a638cd4)</Identifier>
					<Value>48</Value>
				</Attribute>
				<Attribute>
					<Identifier>(0x207c9054, 0x3c841b63)</Identifier>
					<Value>-48</Value>
				</Attribute>
				<Attribute>
					<Identifier>(0x4e7b798a, 0x183beafb)</Identifier>
					<Value>(0x89a08108, 0xc8d1fac1)</Value>
				</Attribute>
				<Attribute>
					<Identifier>(0x527ad68d, 0x16d746a0)</Identifier>
					<Value></Value>
				</Attribute>
				<Attribute>
					<Identifier>(0xad100179, 0xa3c984ab)</Identifier>
					<Value>164</Value>
				</Attribute>
				<Attribute>
					<Identifier>(0xc67a01dc, 0x28ce06c1)</Identifier>
					<Value></Value>
				</Attribute>
				<Attribute>
					<Identifier>(0xce18836a, 0x9c0eb403)</Identifier>
					<Value>2</Value>
				</Attribute>
				<Attribute>
					<Identifier>(0xcfad85b0, 0x7c6d841c)</Identifier>
					<Value>1</Value>
				</Attribute>
				<Attribute>
					<Identifier>(0xfba64161, 0x65304e21)</Identifier>
					<Value></Value>
				</Attribute>
			</Attributes>
		</Box>
		<Box>
			<Identifier>(0x1b10b921, 0x7b3cc877)</Identifier>
			<Name>Temporal filter - GPL</Name>
			<AlgorithmClassIdentifier>(0xb4f9d042, 0x9d79f2e5)</AlgorithmClassIdentifier>
			<Inputs>
				<Input>
					<TypeIdentifier>(0x5ba36127, 0x195feae1)</TypeIdentifier>
					<Name>Input signal</Name>
				</Input>
			</Inputs>
			<Outputs>
				<Output>
					<TypeIdentifier>(0x5ba36127, 0x195feae1)</TypeIdentifier>
					<Name>Filtered signal</Name>
				</Output>
			</Outputs>
			<Settings>
				<Setting>
					<TypeIdentifier>(0x2f2c606c, 0x8512ed68)</TypeIdentifier>
					<Name>Filter method</Name>
					<DefaultValue>Butterworth</DefaultValue>
					<Value>Butterworth</Value>
					<Modifiability>false</Modifiability>
				</Setting>
				<Setting>
					<TypeIdentifier>(0xfa20178e, 0x4cba62e9)</TypeIdentifier>
					<Name>Filter type</Name>
					<DefaultValue>Low pass</DefaultValue>
					<Value>Band pass</Value>
					<Modifiability>false</Modifiability>
				</Setting>
				<Setting>
					<TypeIdentifier>(0x007deef9, 0x2f3e95c6)</TypeIdentifier>
					<Name>Filter order</Name>
					<DefaultValue>4</DefaultValue>
					<Value>4</Value>
					<Modifiability>false</Modifiability>
				</Setting>
				<Setting>
					<TypeIdentifier>(0x512a166f, 0x5c3ef83f)</TypeIdentifier>
					<Name>Low cut frequency (Hz)</Name>
					<DefaultValue>29</DefaultValue>
					<Value>1</Value>
					<Modifiability>false</Modifiability>
				</Setting>
				<Setting>
					<TypeIdentifier>(0x512a166f, 0x5c3ef83f)</TypeIdentifier>
					<Name>High cut frequency (Hz)</Name>
					<DefaultValue>40</DefaultValue>
					<Value>40</Value>
					<Modifiability>false</Modifiability>
				</Setting>
				<Setting>
					<TypeIdentifier>(0x512a166f, 0x5c3ef83f)</TypeIdentifier>
					<Name>Pass band ripple (dB)</Name>
					<DefaultValue>0.5</DefaultValue>
					<Value>0.500000</Value>
					<Modifiability>false</Modifiability>
				</Setting>
			</Settings>
			<Attributes>
				<Attribute>
					<Identifier>(0x1fa7a38f, 0x54edbe0b)</Identifier>
					<Value>-320</Value>
				</Attribute>
				<Attribute>
					<Identifier>(0x1fa963f5, 0x1a638cd4)</Identifier>
					<Value>48</Value>
				</Attribute>
				<Attribute>
					<Identifier>(0x207c9054, 0x3c841b63)</Identifier>
					<Value>-208</Value>
				</Attribute>
				<Attribute>
					<Identifier>(0x4e7b798a, 0x183beafb)</Identifier>
					<Value>(0x27a4ceec, 0x876d6384)</Value>
				</Attribute>
				<Attribute>
					<Identifier>(0xac367a9c, 0x2da95abe)</Identifier>
					<Value>39</Value>
				</Attribute>
				<Attribute>
					<Identifier>(0xad100179, 0xa3c984ab)</Identifier>
					<Value>161</Value>
				</Attribute>
				<Attribute>
					<Identifier>(0xcfad85b0, 0x7c6d841c)</Identifier>
					<Value>2</Value>
				</Attribute>
			</Attributes>
		</Box>
		<Box>
			<Identifier>(0x1d5b71f3, 0x0427834b)</Identifier>
			<Name>ERP plot</Name>
			<AlgorithmClassIdentifier>(0x10dc6917, 0x2b29b2a0)</AlgorithmClassIdentifier>
			<Inputs>
				<Input>
					<TypeIdentifier>(0x6f752dd0, 0x082a321e)</TypeIdentifier>
					<Name>Trigger</Name>
				</Input>
				<Input>
					<TypeIdentifier>(0x544a003e, 0x6dcba5f6)</TypeIdentifier>
					<Name>ERP1</Name>
				</Input>
				<Input>
					<TypeIdentifier>(0x544a003e, 0x6dcba5f6)</TypeIdentifier>
					<Name>Variance1</Name>
				</Input>
				<Input>
					<TypeIdentifier>(0x544a003e, 0x6dcba5f6)</TypeIdentifier>
					<Name>ERP2</Name>
				</Input>
				<Input>
					<TypeIdentifier>(0x544a003e, 0x6dcba5f6)</TypeIdentifier>
					<Name>Variance2</Name>
				</Input>
			</Inputs>
			<Settings>
				<Setting>
					<TypeIdentifier>(0x330306dd, 0x74a95f98)</TypeIdentifier>
					<Name>Filename final figure</Name>
					<DefaultValue></DefaultValue>
					<Value>${Player_ScenarioDirectory}/signals/${externalP300_SubjectName}/p300_${externalP300_SubjectName}_$core{date}_$core{time}.png</Value>
					<Modifiability>false</Modifiability>
				</Setting>
				<Setting>
					<TypeIdentifier>(0x2c132d6e, 0x44ab0d97)</TypeIdentifier>
					<Name>Trigger to save figure</Name>
					<DefaultValue>OVTK_StimulationId_ExperimentStop</DefaultValue>
					<Value>182</Value>
					<Modifiability>false</Modifiability>
				</Setting>
				<Setting>
					<TypeIdentifier>(0x7f45a2a9, 0x7db12219)</TypeIdentifier>
					<Name>Line color 1</Name>
					<DefaultValue>0,0,0</DefaultValue>
					<Value>15,81,13</Value>
					<Modifiability>false</Modifiability>
				</Setting>
				<Setting>
					<TypeIdentifier>(0x79a9edeb, 0x245d83fc)</TypeIdentifier>
					<Name>Line label 1</Name>
					<DefaultValue>curve 1</DefaultValue>
					<Value>target</Value>
					<Modifiability>false</Modifiability>
				</Setting>
				<Setting>
					<TypeIdentifier>(0x7f45a2a9, 0x7db12219)</TypeIdentifier>
					<Name>Line color 2</Name>
					<DefaultValue>0,0,0</DefaultValue>
					<Value>87,14,14</Value>
					<Modifiability>false</Modifiability>
				</Setting>
				<Setting>
					<TypeIdentifier>(0x79a9edeb, 0x245d83fc)</TypeIdentifier>
					<Name>Line label 2</Name>
					<DefaultValue>curve</DefaultValue>
					<Value>non-target</Value>
					<Modifiability>false</Modifiability>
				</Setting>
			</Settings>
			<Attributes>
				<Attribute>
					<Identifier>(0x1fa7a38f, 0x54edbe0b)</Identifier>
					<Value>-112</Value>
				</Attribute>
				<Attribute>
					<Identifier>(0x1fa963f5, 0x1a638cd4)</Identifier>
					<Value>48</Value>
				</Attribute>
				<Attribute>
					<Identifier>(0x207c9054, 0x3c841b63)</Identifier>
					<Value>256</Value>
				</Attribute>
				<Attribute>
					<Identifier>(0x4e7b798a, 0x183beafb)</Identifier>
					<Value>(0x6426093c, 0x90aed000)</Value>
				</Attribute>
				<Attribute>
					<Identifier>(0xad100179, 0xa3c984ab)</Identifier>
					<Value>71</Value>
				</Attribute>
				<Attribute>
					<Identifier>(0xce18836a, 0x9c0eb403)</Identifier>
					<Value>3</Value>
				</Attribute>
				<Attribute>
					<Identifier>(0xcfad85b0, 0x7c6d841c)</Identifier>
					<Value>1</Value>
				</Attribute>
			</Attributes>
		</Box>
		<Box>
			<Identifier>(0x20ee2045, 0x1173220b)</Identifier>
			<Name>Acquisition client</Name>
			<AlgorithmClassIdentifier>(0x35d225cb, 0x3e6e3a5f)</AlgorithmClassIdentifier>
			<Outputs>
				<Output>
					<TypeIdentifier>(0x403488e7, 0x565d70b6)</TypeIdentifier>
					<Name>Experiment information</Name>
				</Output>
				<Output>
					<TypeIdentifier>(0x5ba36127, 0x195feae1)</TypeIdentifier>
					<Name>Signal strea</Name>
				</Output>
				<Output>
					<TypeIdentifier>(0x6f752dd0, 0x082a321e)</TypeIdentifier>
					<Name>Stimulations</Name>
				</Output>
				<Output>
					<TypeIdentifier>(0x013df452, 0xa3a8879a)</TypeIdentifier>
					<Name>Channel localisation</Name>
				</Output>
			</Outputs>
			<Settings>
				<Setting>
					<TypeIdentifier>(0x79a9edeb, 0x245d83fc)</TypeIdentifier>
					<Name>Acquisition server hostname</Name>
					<DefaultValue>${AcquisitionServer_HostName}</DefaultValue>
					<Value>${AcquisitionServer_HostName}</Value>
					<Modifiability>false</Modifiability>
				</Setting>
				<Setting>
					<TypeIdentifier>(0x007deef9, 0x2f3e95c6)</TypeIdentifier>
					<Name>Acquisition server port</Name>
					<DefaultValue>1024</DefaultValue>
					<Value>1024</Value>
					<Modifiability>false</Modifiability>
				</Setting>
			</Settings>
			<Attributes>
				<Attribute>
					<Identifier>(0x1fa7a38f, 0x54edbe0b)</Identifier>
					<Value>-659.000000</Value>
				</Attribute>
				<Attribute>
					<Identifier>(0x1fa963f5, 0x1a638cd4)</Identifier>
					<Value>31</Value>
				</Attribute>
				<Attribute>
					<Identifier>(0x207c9054, 0x3c841b63)</Identifier>
					<Value>704.000000</Value>
				</Attribute>
				<Attribute>
					<Identifier>(0x4e7b798a, 0x183beafb)</Identifier>
					<Value>(0x0ff4da41, 0xc6a874c2)</Value>
				</Attribute>
				<Attribute>
					<Identifier>(0xad100179, 0xa3c984ab)</Identifier>
					<Value>134</Value>
				</Attribute>
				<Attribute>
					<Identifier>(0xc80ce8af, 0xf699f813)</Identifier>
					<Value>4</Value>
				</Attribute>
				<Attribute>
					<Identifier>(0xce18836a, 0x9c0eb403)</Identifier>
					<Value>2</Value>
				</Attribute>
			</Attributes>
		</Box>
		<Box>
			<Identifier>(0x25a4953e, 0x48840e91)</Identifier>
			<Name>Identity</Name>
			<AlgorithmClassIdentifier>(0x5dffe431, 0x35215c50)</AlgorithmClassIdentifier>
			<Inputs>
				<Input>
					<TypeIdentifier>(0x403488e7, 0x565d70b6)</TypeIdentifier>
					<Name>Input stream 1</Name>
				</Input>
				<Input>
					<TypeIdentifier>(0x5ba36127, 0x195feae1)</TypeIdentifier>
					<Name>Input stream 2</Name>
				</Input>
				<Input>
					<TypeIdentifier>(0x6f752dd0, 0x082a321e)</TypeIdentifier>
					<Name>Input stream 3</Name>
				</Input>
			</Inputs>
			<Outputs>
				<Output>
					<TypeIdentifier>(0x403488e7, 0x565d70b6)</TypeIdentifier>
					<Name>Output stream 1</Name>
				</Output>
				<Output>
					<TypeIdentifier>(0x5ba36127, 0x195feae1)</TypeIdentifier>
					<Name>Output stream 2</Name>
				</Output>
				<Output>
					<TypeIdentifier>(0x6f752dd0, 0x082a321e)</TypeIdentifier>
					<Name>Output stream 3</Name>
				</Output>
			</Outputs>
			<Attributes>
				<Attribute>
					<Identifier>(0x17ee7c08, 0x94c14893)</Identifier>
					<Value></Value>
				</Attribute>
				<Attribute>
					<Identifier>(0x1fa7a38f, 0x54edbe0b)</Identifier>
					<Value>-544</Value>
				</Attribute>
				<Attribute>
					<Identifier>(0x1fa963f5, 0x1a638cd4)</Identifier>
					<Value>48</Value>
				</Attribute>
				<Attribute>
					<Identifier>(0x207c9054, 0x3c841b63)</Identifier>
					<Value>208</Value>
				</Attribute>
				<Attribute>
					<Identifier>(0x30a4e5c9, 0x83502953)</Identifier>
					<Value></Value>
				</Attribute>
				<Attribute>
					<Identifier>(0x4e7b798a, 0x183beafb)</Identifier>
					<Value>(0x92ff5cdb, 0x273984ce)</Value>
				</Attribute>
				<Attribute>
					<Identifier>(0x527ad68d, 0x16d746a0)</Identifier>
					<Value></Value>
				</Attribute>
				<Attribute>
					<Identifier>(0xac367a9c, 0x2da95abe)</Identifier>
					<Value>65</Value>
				</Attribute>
				<Attribute>
					<Identifier>(0xad100179, 0xa3c984ab)</Identifier>
					<Value>69</Value>
				</Attribute>
				<Attribute>
					<Identifier>(0xfba64161, 0x65304e21)</Identifier>
					<Value></Value>
				</Attribute>
			</Attributes>
		</Box>
		<Box>
			<Identifier>(0x2c59bb68, 0x607f56d9)</Identifier>
			<Name>Stimulation based epoching</Name>
			<AlgorithmClassIdentifier>(0x426163d1, 0x324237b0)</AlgorithmClassIdentifier>
			<Inputs>
				<Input>
					<TypeIdentifier>(0x5ba36127, 0x195feae1)</TypeIdentifier>
					<Name>Input signal</Name>
				</Input>
				<Input>
					<TypeIdentifier>(0x6f752dd0, 0x082a321e)</TypeIdentifier>
					<Name>Input stimulations</Name>
				</Input>
			</Inputs>
			<Outputs>
				<Output>
					<TypeIdentifier>(0x5ba36127, 0x195feae1)</TypeIdentifier>
					<Name>Epoched signal</Name>
				</Output>
				<Output>
					<TypeIdentifier>(0x6f752dd0, 0x082a321e)</TypeIdentifier>
					<Name>Resynced stimulations</Name>
				</Output>
			</Outputs>
			<Settings>
				<Setting>
					<TypeIdentifier>(0x512a166f, 0x5c3ef83f)</TypeIdentifier>
					<Name>Epoch duration (in sec)</Name>
					<DefaultValue>1</DefaultValue>
					<Value>0.6</Value>
					<Modifiability>false</Modifiability>
				</Setting>
				<Setting>
					<TypeIdentifier>(0x512a166f, 0x5c3ef83f)</TypeIdentifier>
					<Name>Epoch offset (in sec)</Name>
					<DefaultValue>0.5</DefaultValue>
					<Value>0</Value>
					<Modifiability>false</Modifiability>
				</Setting>
				<Setting>
					<TypeIdentifier>(0x2c132d6e, 0x44ab0d97)</TypeIdentifier>
					<Name>Stimulation to epoch from</Name>
					<DefaultValue>OVTK_GDF_VEP</DefaultValue>
					<Value>195</Value>
					<Modifiability>false</Modifiability>
				</Setting>
			</Settings>
			<Attributes>
				<Attribute>
					<Identifier>(0x1fa7a38f, 0x54edbe0b)</Identifier>
					<Value>-272</Value>
				</Attribute>
				<Attribute>
					<Identifier>(0x1fa963f5, 0x1a638cd4)</Identifier>
					<Value>31</Value>
				</Attribute>
				<Attribute>
					<Identifier>(0x207c9054, 0x3c841b63)</Identifier>
					<Value>704</Value>
				</Attribute>
				<Attribute>
					<Identifier>(0x4e7b798a, 0x183beafb)</Identifier>
					<Value>(0x95ec5f7e, 0x885aeb68)</Value>
				</Attribute>
				<Attribute>
					<Identifier>(0xad100179, 0xa3c984ab)</Identifier>
					<Value>208</Value>
				</Attribute>
				<Attribute>
					<Identifier>(0xc80ce8af, 0xf699f813)</Identifier>
					<Value>2</Value>
				</Attribute>
				<Attribute>
					<Identifier>(0xce18836a, 0x9c0eb403)</Identifier>
					<Value>3</Value>
				</Attribute>
				<Attribute>
					<Identifier>(0xcfad85b0, 0x7c6d841c)</Identifier>
					<Value>2</Value>
				</Attribute>
			</Attributes>
		</Box>
		<Box>
			<Identifier>(0x329c6c0d, 0x3ea1fb35)</Identifier>
			<Name>Classifier processor</Name>
			<AlgorithmClassIdentifier>(0x5fe23d17, 0x95b0452c)</AlgorithmClassIdentifier>
			<Inputs>
				<Input>
					<TypeIdentifier>(0x17341935, 0x152ff448)</TypeIdentifier>
					<Name>Features</Name>
				</Input>
			</Inputs>
			<Outputs>
				<Output>
					<TypeIdentifier>(0x6f752dd0, 0x082a321e)</TypeIdentifier>
					<Name>Labels</Name>
				</Output>
				<Output>
					<TypeIdentifier>(0x544a003e, 0x6dcba5f6)</TypeIdentifier>
					<Name>Classification state</Name>
				</Output>
			</Outputs>
			<Settings>
				<Setting>
					<TypeIdentifier>(0x330306dd, 0x74a95f98)</TypeIdentifier>
					<Name>Filename to load configuration from</Name>
					<DefaultValue></DefaultValue>
					<Value>${Player_ScenarioDirectory}/${externalP300_paramFile}-classifier.cfg</Value>
					<Modifiability>false</Modifiability>
				</Setting>
			</Settings>
			<Attributes>
				<Attribute>
					<Identifier>(0x1fa7a38f, 0x54edbe0b)</Identifier>
					<Value>-128.000000</Value>
				</Attribute>
				<Attribute>
					<Identifier>(0x1fa963f5, 0x1a638cd4)</Identifier>
					<Value>31</Value>
				</Attribute>
				<Attribute>
					<Identifier>(0x207c9054, 0x3c841b63)</Identifier>
					<Value>704.000000</Value>
				</Attribute>
				<Attribute>
					<Identifier>(0x4e7b798a, 0x183beafb)</Identifier>
					<Value>(0x3ff76da6, 0xfbeb7225)</Value>
				</Attribute>
				<Attribute>
					<Identifier>(0xad100179, 0xa3c984ab)</Identifier>
					<Value>153</Value>
				</Attribute>
				<Attribute>
					<Identifier>(0xc73e83ec, 0xf855c5bc)</Identifier>
					<Value>false</Value>
				</Attribute>
				<Attribute>
					<Identifier>(0xc80ce8af, 0xf699f813)</Identifier>
					<Value>2</Value>
				</Attribute>
				<Attribute>
					<Identifier>(0xce18836a, 0x9c0eb403)</Identifier>
					<Value>1</Value>
				</Attribute>
				<Attribute>
					<Identifier>(0xcfad85b0, 0x7c6d841c)</Identifier>
					<Value>1</Value>
				</Attribute>
			</Attributes>
		</Box>
		<Box>
			<Identifier>(0x3706b132, 0x00c4e50d)</Identifier>
			<Name>Signal Decimation</Name>
			<AlgorithmClassIdentifier>(0x012f4bea, 0x3be37c66)</AlgorithmClassIdentifier>
			<Inputs>
				<Input>
					<TypeIdentifier>(0x5ba36127, 0x195feae1)</TypeIdentifier>
					<Name>Input signal</Name>
				</Input>
			</Inputs>
			<Outputs>
				<Output>
					<TypeIdentifier>(0x5ba36127, 0x195feae1)</TypeIdentifier>
					<Name>Output signal</Name>
				</Output>
			</Outputs>
			<Settings>
				<Setting>
					<TypeIdentifier>(0x007deef9, 0x2f3e95c6)</TypeIdentifier>
					<Name>Decimation factor</Name>
					<DefaultValue>8</DefaultValue>
					<Value>4</Value>
					<Modifiability>false</Modifiability>
				</Setting>
			</Settings>
			<Attributes>
				<Attribute>
					<Identifier>(0x1fa7a38f, 0x54edbe0b)</Identifier>
					<Value>-416</Value>
				</Attribute>
				<Attribute>
					<Identifier>(0x1fa963f5, 0x1a638cd4)</Identifier>
					<Value>31</Value>
				</Attribute>
				<Attribute>
					<Identifier>(0x207c9054, 0x3c841b63)</Identifier>
					<Value>704</Value>
				</Attribute>
				<Attribute>
					<Identifier>(0x4e7b798a, 0x183beafb)</Identifier>
					<Value>(0x5082af41, 0xd0fbf4cb)</Value>
				</Attribute>
				<Attribute>
					<Identifier>(0xad100179, 0xa3c984ab)</Identifier>
					<Value>139</Value>
				</Attribute>
				<Attribute>
					<Identifier>(0xc80ce8af, 0xf699f813)</Identifier>
					<Value>1</Value>
				</Attribute>
				<Attribute>
					<Identifier>(0xce18836a, 0x9c0eb403)</Identifier>
					<Value>1</Value>
				</Attribute>
				<Attribute>
					<Identifier>(0xcfad85b0, 0x7c6d841c)</Identifier>
					<Value>1</Value>
				</Attribute>
			</Attributes>
		</Box>
		<Box>
			<Identifier>(0x39f63dcd, 0x7ef5f905)</Identifier>
			<Name>Stimulation based epoching</Name>
			<AlgorithmClassIdentifier>(0x426163d1, 0x324237b0)</AlgorithmClassIdentifier>
			<Inputs>
				<Input>
					<TypeIdentifier>(0x5ba36127, 0x195feae1)</TypeIdentifier>
					<Name>Input signal</Name>
				</Input>
				<Input>
					<TypeIdentifier>(0x6f752dd0, 0x082a321e)</TypeIdentifier>
					<Name>Input stimulations</Name>
				</Input>
			</Inputs>
			<Outputs>
				<Output>
					<TypeIdentifier>(0x5ba36127, 0x195feae1)</TypeIdentifier>
					<Name>Epoched signal</Name>
				</Output>
				<Output>
					<TypeIdentifier>(0x6f752dd0, 0x082a321e)</TypeIdentifier>
					<Name>Resynced stimulations</Name>
				</Output>
			</Outputs>
			<Settings>
				<Setting>
					<TypeIdentifier>(0x512a166f, 0x5c3ef83f)</TypeIdentifier>
					<Name>Epoch duration (in sec)</Name>
					<DefaultValue>1</DefaultValue>
					<Value>0.6</Value>
					<Modifiability>false</Modifiability>
				</Setting>
				<Setting>
					<TypeIdentifier>(0x512a166f, 0x5c3ef83f)</TypeIdentifier>
					<Name>Epoch offset (in sec)</Name>
					<DefaultValue>0.5</DefaultValue>
					<Value>0</Value>
					<Modifiability>false</Modifiability>
				</Setting>
				<Setting>
					<TypeIdentifier>(0x2c132d6e, 0x44ab0d97)</TypeIdentifier>
					<Name>Stimulation to epoch from</Name>
					<DefaultValue>OVTK_GDF_VEP</DefaultValue>
					<Value>191</Value>
					<Modifiability>false</Modifiability>
				</Setting>
			</Settings>
			<Attributes>
				<Attribute>
					<Identifier>(0x1fa7a38f, 0x54edbe0b)</Identifier>
					<Value>-304</Value>
				</Attribute>
				<Attribute>
					<Identifier>(0x1fa963f5, 0x1a638cd4)</Identifier>
					<Value>31</Value>
				</Attribute>
				<Attribute>
					<Identifier>(0x207c9054, 0x3c841b63)</Identifier>
					<Value>144</Value>
				</Attribute>
				<Attribute>
					<Identifier>(0x4e7b798a, 0x183beafb)</Identifier>
					<Value>(0x95ec5f7e, 0x885aeb68)</Value>
				</Attribute>
				<Attribute>
					<Identifier>(0xad100179, 0xa3c984ab)</Identifier>
					<Value>208</Value>
				</Attribute>
				<Attribute>
					<Identifier>(0xc80ce8af, 0xf699f813)</Identifier>
					<Value>2</Value>
				</Attribute>
				<Attribute>
					<Identifier>(0xce18836a, 0x9c0eb403)</Identifier>
					<Value>3</Value>
				</Attribute>
				<Attribute>
					<Identifier>(0xcfad85b0, 0x7c6d841c)</Identifier>
					<Value>2</Value>
				</Attribute>
			</Attributes>
		</Box>
		<Box>
			<Identifier>(0x4cab91da, 0x5e03f1e6)</Identifier>
			<Name>Identity</Name>
			<AlgorithmClassIdentifier>(0x5dffe431, 0x35215c50)</AlgorithmClassIdentifier>
			<Inputs>
				<Input>
					<TypeIdentifier>(0x6f752dd0, 0x082a321e)</TypeIdentifier>
					<Name>Input stream 1</Name>
				</Input>
			</Inputs>
			<Outputs>
				<Output>
					<TypeIdentifier>(0x6f752dd0, 0x082a321e)</TypeIdentifier>
					<Name>Output stream 1</Name>
				</Output>
			</Outputs>
			<Attributes>
				<Attribute>
					<Identifier>(0x17ee7c08, 0x94c14893)</Identifier>
					<Value></Value>
				</Attribute>
				<Attribute>
					<Identifier>(0x1fa7a38f, 0x54edbe0b)</Identifier>
					<Value>-368</Value>
				</Attribute>
				<Attribute>
					<Identifier>(0x1fa963f5, 0x1a638cd4)</Identifier>
					<Value>48</Value>
				</Attribute>
				<Attribute>
					<Identifier>(0x207c9054, 0x3c841b63)</Identifier>
					<Value>1232</Value>
				</Attribute>
				<Attribute>
					<Identifier>(0x30a4e5c9, 0x83502953)</Identifier>
					<Value></Value>
				</Attribute>
				<Attribute>
					<Identifier>(0x4e7b798a, 0x183beafb)</Identifier>
					<Value>(0x92ff5cdb, 0x273984ce)</Value>
				</Attribute>
				<Attribute>
					<Identifier>(0x527ad68d, 0x16d746a0)</Identifier>
					<Value></Value>
				</Attribute>
				<Attribute>
					<Identifier>(0xac367a9c, 0x2da95abe)</Identifier>
					<Value>65</Value>
				</Attribute>
				<Attribute>
					<Identifier>(0xad100179, 0xa3c984ab)</Identifier>
					<Value>69</Value>
				</Attribute>
				<Attribute>
					<Identifier>(0xfba64161, 0x65304e21)</Identifier>
					<Value></Value>
				</Attribute>
			</Attributes>
		</Box>
		<Box>
			<Identifier>(0x4cddfdbe, 0x37b0e8b9)</Identifier>
			<Name>Stimulation based epoching</Name>
			<AlgorithmClassIdentifier>(0x426163d1, 0x324237b0)</AlgorithmClassIdentifier>
			<Inputs>
				<Input>
					<TypeIdentifier>(0x5ba36127, 0x195feae1)</TypeIdentifier>
					<Name>Input signal</Name>
				</Input>
				<Input>
					<TypeIdentifier>(0x6f752dd0, 0x082a321e)</TypeIdentifier>
					<Name>Input stimulations</Name>
				</Input>
			</Inputs>
			<Outputs>
				<Output>
					<TypeIdentifier>(0x5ba36127, 0x195feae1)</TypeIdentifier>
					<Name>Epoched signal</Name>
				</Output>
				<Output>
					<TypeIdentifier>(0x6f752dd0, 0x082a321e)</TypeIdentifier>
					<Name>Resynced stimulations</Name>
				</Output>
			</Outputs>
			<Settings>
				<Setting>
					<TypeIdentifier>(0x512a166f, 0x5c3ef83f)</TypeIdentifier>
					<Name>Epoch duration (in sec)</Name>
					<DefaultValue>1</DefaultValue>
					<Value>0.6</Value>
					<Modifiability>false</Modifiability>
				</Setting>
				<Setting>
					<TypeIdentifier>(0x512a166f, 0x5c3ef83f)</TypeIdentifier>
					<Name>Epoch offset (in sec)</Name>
					<DefaultValue>0.5</DefaultValue>
					<Value>0</Value>
					<Modifiability>false</Modifiability>
				</Setting>
				<Setting>
					<TypeIdentifier>(0x2c132d6e, 0x44ab0d97)</TypeIdentifier>
					<Name>Stimulation to epoch from</Name>
					<DefaultValue>OVTK_GDF_VEP</DefaultValue>
					<Value>192</Value>
					<Modifiability>false</Modifiability>
				</Setting>
			</Settings>
			<Attributes>
				<Attribute>
					<Identifier>(0x1fa7a38f, 0x54edbe0b)</Identifier>
					<Value>-304</Value>
				</Attribute>
				<Attribute>
					<Identifier>(0x1fa963f5, 0x1a638cd4)</Identifier>
					<Value>31</Value>
				</Attribute>
				<Attribute>
					<Identifier>(0x207c9054, 0x3c841b63)</Identifier>
					<Value>432</Value>
				</Attribute>
				<Attribute>
					<Identifier>(0x4e7b798a, 0x183beafb)</Identifier>
					<Value>(0x95ec5f7e, 0x885aeb68)</Value>
				</Attribute>
				<Attribute>
					<Identifier>(0xad100179, 0xa3c984ab)</Identifier>
					<Value>208</Value>
				</Attribute>
				<Attribute>
					<Identifier>(0xc80ce8af, 0xf699f813)</Identifier>
					<Value>2</Value>
				</Attribute>
				<Attribute>
					<Identifier>(0xce18836a, 0x9c0eb403)</Identifier>
					<Value>3</Value>
				</Attribute>
				<Attribute>
					<Identifier>(0xcfad85b0, 0x7c6d841c)</Identifier>
					<Value>2</Value>
				</Attribute>
			</Attributes>
		</Box>
		<Box>
			<Identifier>(0x5164de44, 0x71f34b55)</Identifier>
			<Name>Epoch variance</Name>
			<AlgorithmClassIdentifier>(0x335384ea, 0x88c917d9)</AlgorithmClassIdentifier>
			<Inputs>
				<Input>
					<TypeIdentifier>(0x544a003e, 0x6dcba5f6)</TypeIdentifier>
					<Name>Input epochs</Name>
				</Input>
			</Inputs>
			<Outputs>
				<Output>
					<TypeIdentifier>(0x544a003e, 0x6dcba5f6)</TypeIdentifier>
					<Name>Averaged epochs</Name>
				</Output>
				<Output>
					<TypeIdentifier>(0x544a003e, 0x6dcba5f6)</TypeIdentifier>
					<Name>Variance of epochs</Name>
				</Output>
				<Output>
					<TypeIdentifier>(0x544a003e, 0x6dcba5f6)</TypeIdentifier>
					<Name>Confidence bounds</Name>
				</Output>
			</Outputs>
			<Settings>
				<Setting>
					<TypeIdentifier>(0x6530bdb1, 0xd057bbfe)</TypeIdentifier>
					<Name>Averaging type</Name>
					<DefaultValue>Moving epoch average</DefaultValue>
					<Value>Cumulative average</Value>
					<Modifiability>false</Modifiability>
				</Setting>
				<Setting>
					<TypeIdentifier>(0x007deef9, 0x2f3e95c6)</TypeIdentifier>
					<Name>Epoch count</Name>
					<DefaultValue>4</DefaultValue>
					<Value>4</Value>
					<Modifiability>false</Modifiability>
				</Setting>
				<Setting>
					<TypeIdentifier>(0x512a166f, 0x5c3ef83f)</TypeIdentifier>
					<Name>Significance level</Name>
					<DefaultValue>0.01</DefaultValue>
					<Value>0.05</Value>
					<Modifiability>false</Modifiability>
				</Setting>
			</Settings>
			<Attributes>
				<Attribute>
					<Identifier>(0x1fa7a38f, 0x54edbe0b)</Identifier>
					<Value>-224.000000</Value>
				</Attribute>
				<Attribute>
					<Identifier>(0x1fa963f5, 0x1a638cd4)</Identifier>
					<Value>48</Value>
				</Attribute>
				<Attribute>
					<Identifier>(0x207c9054, 0x3c841b63)</Identifier>
					<Value>144.000000</Value>
				</Attribute>
				<Attribute>
					<Identifier>(0x4e7b798a, 0x183beafb)</Identifier>
					<Value>(0xe7fb819b, 0x3ff4203d)</Value>
				</Attribute>
				<Attribute>
					<Identifier>(0x527ad68d, 0x16d746a0)</Identifier>
					<Value></Value>
				</Attribute>
				<Attribute>
					<Identifier>(0xad100179, 0xa3c984ab)</Identifier>
					<Value>117</Value>
				</Attribute>
				<Attribute>
					<Identifier>(0xc73e83ec, 0xf855c5bc)</Identifier>
					<Value>false</Value>
				</Attribute>
				<Attribute>
					<Identifier>(0xc80ce8af, 0xf699f813)</Identifier>
					<Value>3</Value>
				</Attribute>
				<Attribute>
					<Identifier>(0xce18836a, 0x9c0eb403)</Identifier>
					<Value>3</Value>
				</Attribute>
				<Attribute>
					<Identifier>(0xcfad85b0, 0x7c6d841c)</Identifier>
					<Value>1</Value>
				</Attribute>
			</Attributes>
		</Box>
		<Box>
			<Identifier>(0x563ffbad, 0x25b157d0)</Identifier>
			<Name>Temporal filter - GPL</Name>
			<AlgorithmClassIdentifier>(0xb4f9d042, 0x9d79f2e5)</AlgorithmClassIdentifier>
			<Inputs>
				<Input>
					<TypeIdentifier>(0x5ba36127, 0x195feae1)</TypeIdentifier>
					<Name>Input signal</Name>
				</Input>
			</Inputs>
			<Outputs>
				<Output>
					<TypeIdentifier>(0x5ba36127, 0x195feae1)</TypeIdentifier>
					<Name>Filtered signal</Name>
				</Output>
			</Outputs>
			<Settings>
				<Setting>
					<TypeIdentifier>(0x2f2c606c, 0x8512ed68)</TypeIdentifier>
					<Name>Filter method</Name>
					<DefaultValue>Butterworth</DefaultValue>
					<Value>Butterworth</Value>
					<Modifiability>false</Modifiability>
				</Setting>
				<Setting>
					<TypeIdentifier>(0xfa20178e, 0x4cba62e9)</TypeIdentifier>
					<Name>Filter type</Name>
					<DefaultValue>Low pass</DefaultValue>
					<Value>Band pass</Value>
					<Modifiability>false</Modifiability>
				</Setting>
				<Setting>
					<TypeIdentifier>(0x007deef9, 0x2f3e95c6)</TypeIdentifier>
					<Name>Filter order</Name>
					<DefaultValue>4</DefaultValue>
					<Value>4</Value>
					<Modifiability>false</Modifiability>
				</Setting>
				<Setting>
					<TypeIdentifier>(0x512a166f, 0x5c3ef83f)</TypeIdentifier>
					<Name>Low cut frequency (Hz)</Name>
					<DefaultValue>29</DefaultValue>
					<Value>1.000000</Value>
					<Modifiability>false</Modifiability>
				</Setting>
				<Setting>
					<TypeIdentifier>(0x512a166f, 0x5c3ef83f)</TypeIdentifier>
					<Name>High cut frequency (Hz)</Name>
					<DefaultValue>40</DefaultValue>
					<Value>15</Value>
					<Modifiability>false</Modifiability>
				</Setting>
				<Setting>
					<TypeIdentifier>(0x512a166f, 0x5c3ef83f)</TypeIdentifier>
					<Name>Pass band ripple (dB)</Name>
					<DefaultValue>0.5</DefaultValue>
					<Value>0.500000</Value>
					<Modifiability>false</Modifiability>
				</Setting>
			</Settings>
			<Attributes>
				<Attribute>
					<Identifier>(0x1fa7a38f, 0x54edbe0b)</Identifier>
					<Value>-480</Value>
				</Attribute>
				<Attribute>
					<Identifier>(0x1fa963f5, 0x1a638cd4)</Identifier>
					<Value>48</Value>
				</Attribute>
				<Attribute>
					<Identifier>(0x207c9054, 0x3c841b63)</Identifier>
					<Value>704</Value>
				</Attribute>
				<Attribute>
					<Identifier>(0x4e7b798a, 0x183beafb)</Identifier>
					<Value>(0x27a4ceec, 0x876d6384)</Value>
				</Attribute>
				<Attribute>
					<Identifier>(0xac367a9c, 0x2da95abe)</Identifier>
					<Value>39</Value>
				</Attribute>
				<Attribute>
					<Identifier>(0xad100179, 0xa3c984ab)</Identifier>
					<Value>161</Value>
				</Attribute>
			</Attributes>
		</Box>
		<Box>
			<Identifier>(0x5905c5f5, 0x32d562d1)</Identifier>
			<Name>Channel Selector</Name>
			<AlgorithmClassIdentifier>(0x361722e8, 0x311574e8)</AlgorithmClassIdentifier>
			<Inputs>
				<Input>
					<TypeIdentifier>(0x5ba36127, 0x195feae1)</TypeIdentifier>
					<Name>Input signal</Name>
				</Input>
			</Inputs>
			<Outputs>
				<Output>
					<TypeIdentifier>(0x5ba36127, 0x195feae1)</TypeIdentifier>
					<Name>Output signal</Name>
				</Output>
			</Outputs>
			<Settings>
				<Setting>
					<TypeIdentifier>(0x79a9edeb, 0x245d83fc)</TypeIdentifier>
					<Name>Channel List</Name>
					<DefaultValue>:</DefaultValue>
					<Value>1</Value>
					<Modifiability>false</Modifiability>
				</Setting>
				<Setting>
					<TypeIdentifier>(0x3bcf9e67, 0x0c23994d)</TypeIdentifier>
					<Name>Action</Name>
					<DefaultValue>Select</DefaultValue>
					<Value>Select</Value>
					<Modifiability>false</Modifiability>
				</Setting>
				<Setting>
					<TypeIdentifier>(0x666f25e9, 0x3e5738d6)</TypeIdentifier>
					<Name>Channel Matching Method</Name>
					<DefaultValue>Smart</DefaultValue>
					<Value>Index</Value>
					<Modifiability>false</Modifiability>
				</Setting>
			</Settings>
			<Attributes>
				<Attribute>
					<Identifier>(0x1fa7a38f, 0x54edbe0b)</Identifier>
					<Value>-368.000000</Value>
				</Attribute>
				<Attribute>
					<Identifier>(0x1fa963f5, 0x1a638cd4)</Identifier>
					<Value>48</Value>
				</Attribute>
				<Attribute>
					<Identifier>(0x207c9054, 0x3c841b63)</Identifier>
					<Value>272.000000</Value>
				</Attribute>
				<Attribute>
					<Identifier>(0x30a4e5c9, 0x83502953)</Identifier>
					<Value></Value>
				</Attribute>
				<Attribute>
					<Identifier>(0x4e7b798a, 0x183beafb)</Identifier>
					<Value>(0x95781be1, 0xa38dce2d)</Value>
				</Attribute>
				<Attribute>
					<Identifier>(0x527ad68d, 0x16d746a0)</Identifier>
					<Value></Value>
				</Attribute>
				<Attribute>
					<Identifier>(0xad100179, 0xa3c984ab)</Identifier>
					<Value>132</Value>
				</Attribute>
				<Attribute>
					<Identifier>(0xc73e83ec, 0xf855c5bc)</Identifier>
					<Value>false</Value>
				</Attribute>
				<Attribute>
					<Identifier>(0xc80ce8af, 0xf699f813)</Identifier>
					<Value>1</Value>
				</Attribute>
				<Attribute>
					<Identifier>(0xce18836a, 0x9c0eb403)</Identifier>
					<Value>3</Value>
				</Attribute>
				<Attribute>
					<Identifier>(0xcfad85b0, 0x7c6d841c)</Identifier>
					<Value>1</Value>
				</Attribute>
			</Attributes>
		</Box>
		<Box>
			<Identifier>(0x5fd6c4c7, 0x21294a03)</Identifier>
			<Name>Signal display</Name>
			<AlgorithmClassIdentifier>(0x0055be5f, 0x087bdd12)</AlgorithmClassIdentifier>
			<Inputs>
				<Input>
					<TypeIdentifier>(0x544a003e, 0x6dcba5f6)</TypeIdentifier>
					<Name>Signal</Name>
				</Input>
				<Input>
					<TypeIdentifier>(0x6f752dd0, 0x082a321e)</TypeIdentifier>
					<Name>Stimulations</Name>
				</Input>
			</Inputs>
			<Settings>
				<Setting>
					<TypeIdentifier>(0x512a166f, 0x5c3ef83f)</TypeIdentifier>
					<Name>Time Scale</Name>
					<DefaultValue>10</DefaultValue>
					<Value>10</Value>
					<Modifiability>false</Modifiability>
				</Setting>
				<Setting>
					<TypeIdentifier>(0x5de046a6, 0x086340aa)</TypeIdentifier>
					<Name>Display Mode</Name>
					<DefaultValue>Scan</DefaultValue>
					<Value>Scan</Value>
					<Modifiability>false</Modifiability>
				</Setting>
				<Setting>
					<TypeIdentifier>(0x2cdb2f0b, 0x12f231ea)</TypeIdentifier>
					<Name>EEG display</Name>
					<DefaultValue>true</DefaultValue>
					<Value>true</Value>
					<Modifiability>false</Modifiability>
				</Setting>
				<Setting>
					<TypeIdentifier>(0x2cdb2f0b, 0x12f231ea)</TypeIdentifier>
					<Name>Manual Vertical Scale</Name>
					<DefaultValue>false</DefaultValue>
					<Value>false</Value>
					<Modifiability>false</Modifiability>
				</Setting>
				<Setting>
					<TypeIdentifier>(0x512a166f, 0x5c3ef83f)</TypeIdentifier>
					<Name>Vertical Scale</Name>
					<DefaultValue>100</DefaultValue>
					<Value>100</Value>
					<Modifiability>false</Modifiability>
				</Setting>
			</Settings>
			<Attributes>
				<Attribute>
					<Identifier>(0x1fa7a38f, 0x54edbe0b)</Identifier>
					<Value>-162.000000</Value>
				</Attribute>
				<Attribute>
					<Identifier>(0x1fa963f5, 0x1a638cd4)</Identifier>
					<Value>31</Value>
				</Attribute>
				<Attribute>
					<Identifier>(0x207c9054, 0x3c841b63)</Identifier>
					<Value>-96.000000</Value>
				</Attribute>
				<Attribute>
					<Identifier>(0x4e7b798a, 0x183beafb)</Identifier>
					<Value>(0x8420627f, 0x258204fa)</Value>
				</Attribute>
				<Attribute>
					<Identifier>(0xad100179, 0xa3c984ab)</Identifier>
					<Value>110</Value>
				</Attribute>
				<Attribute>
					<Identifier>(0xc73e83ec, 0xf855c5bc)</Identifier>
					<Value>false</Value>
				</Attribute>
				<Attribute>
					<Identifier>(0xce18836a, 0x9c0eb403)</Identifier>
					<Value>5</Value>
				</Attribute>
				<Attribute>
					<Identifier>(0xcfad85b0, 0x7c6d841c)</Identifier>
					<Value>2</Value>
				</Attribute>
			</Attributes>
		</Box>
		<Box>
			<Identifier>(0x641cd641, 0x7b1a71b3)</Identifier>
			<Name>Feature aggregator</Name>
			<AlgorithmClassIdentifier>(0x00682417, 0x453635f9)</AlgorithmClassIdentifier>
			<Inputs>
				<Input>
					<TypeIdentifier>(0x544a003e, 0x6dcba5f6)</TypeIdentifier>
					<Name>Input stream 1</Name>
				</Input>
			</Inputs>
			<Outputs>
				<Output>
					<TypeIdentifier>(0x17341935, 0x152ff448)</TypeIdentifier>
					<Name>Feature vector stream</Name>
				</Output>
			</Outputs>
			<Attributes>
				<Attribute>
					<Identifier>(0x1fa7a38f, 0x54edbe0b)</Identifier>
					<Value>-208</Value>
				</Attribute>
				<Attribute>
					<Identifier>(0x1fa963f5, 0x1a638cd4)</Identifier>
					<Value>48</Value>
				</Attribute>
				<Attribute>
					<Identifier>(0x207c9054, 0x3c841b63)</Identifier>
					<Value>704</Value>
				</Attribute>
				<Attribute>
					<Identifier>(0x4e7b798a, 0x183beafb)</Identifier>
					<Value>(0xb5d15cc9, 0x6c8c28fb)</Value>
				</Attribute>
				<Attribute>
					<Identifier>(0xac367a9c, 0x2da95abe)</Identifier>
					<Value>26</Value>
				</Attribute>
				<Attribute>
					<Identifier>(0xad100179, 0xa3c984ab)</Identifier>
					<Value>137</Value>
				</Attribute>
				<Attribute>
					<Identifier>(0xc80ce8af, 0xf699f813)</Identifier>
					<Value>1</Value>
				</Attribute>
				<Attribute>
					<Identifier>(0xcfad85b0, 0x7c6d841c)</Identifier>
					<Value>1</Value>
				</Attribute>
				<Attribute>
					<Identifier>(0xfba64161, 0x65304e21)</Identifier>
					<Value></Value>
				</Attribute>
			</Attributes>
		</Box>
		<Box>
			<Identifier>(0x6c153974, 0x133ff47d)</Identifier>
			<Name>SharedMemoryWriter</Name>
			<AlgorithmClassIdentifier>(0xacc272dd, 0xc1bdc1b1)</AlgorithmClassIdentifier>
			<Inputs>
				<Input>
					<TypeIdentifier>(0x544a003e, 0x6dcba5f6)</TypeIdentifier>
					<Name>prediction1</Name>
				</Input>
			</Inputs>
			<Settings>
				<Setting>
					<TypeIdentifier>(0x79a9edeb, 0x245d83fc)</TypeIdentifier>
					<Name>SharedMemoryName</Name>
					<DefaultValue>SharedMemory_P300Stimulator</DefaultValue>
					<Value>SharedMemory_P300Stimulator</Value>
					<Modifiability>false</Modifiability>
				</Setting>
			</Settings>
			<Attributes>
				<Attribute>
					<Identifier>(0x1fa7a38f, 0x54edbe0b)</Identifier>
					<Value>-48.000000</Value>
				</Attribute>
				<Attribute>
					<Identifier>(0x1fa963f5, 0x1a638cd4)</Identifier>
					<Value>65</Value>
				</Attribute>
				<Attribute>
					<Identifier>(0x207c9054, 0x3c841b63)</Identifier>
					<Value>704.000000</Value>
				</Attribute>
				<Attribute>
					<Identifier>(0x4e7b798a, 0x183beafb)</Identifier>
					<Value>(0x41eb1898, 0xb5cc4dd4)</Value>
				</Attribute>
				<Attribute>
					<Identifier>(0x527ad68d, 0x16d746a0)</Identifier>
					<Value></Value>
				</Attribute>
				<Attribute>
					<Identifier>(0xad100179, 0xa3c984ab)</Identifier>
					<Value>163</Value>
				</Attribute>
				<Attribute>
					<Identifier>(0xc73e83ec, 0xf855c5bc)</Identifier>
					<Value>false</Value>
				</Attribute>
				<Attribute>
					<Identifier>(0xce18836a, 0x9c0eb403)</Identifier>
					<Value>1</Value>
				</Attribute>
				<Attribute>
					<Identifier>(0xcfad85b0, 0x7c6d841c)</Identifier>
					<Value>1</Value>
				</Attribute>
				<Attribute>
					<Identifier>(0xfba64161, 0x65304e21)</Identifier>
					<Value></Value>
				</Attribute>
			</Attributes>
		</Box>
		<Box>
			<Identifier>(0x71eeb870, 0x43000732)</Identifier>
			<Name>xDAWN Spatial Filter</Name>
			<AlgorithmClassIdentifier>(0xdd332c6c, 0x195b4fd4)</AlgorithmClassIdentifier>
			<Inputs>
				<Input>
					<TypeIdentifier>(0x5ba36127, 0x195feae1)</TypeIdentifier>
					<Name>Input Signal</Name>
				</Input>
			</Inputs>
			<Outputs>
				<Output>
					<TypeIdentifier>(0x5ba36127, 0x195feae1)</TypeIdentifier>
					<Name>Output Signal</Name>
				</Output>
			</Outputs>
			<Settings>
				<Setting>
					<TypeIdentifier>(0x79a9edeb, 0x245d83fc)</TypeIdentifier>
					<Name>Spatial Fitler Coefficients</Name>
					<DefaultValue>1;0;0;0;0;1;0;0;0;0;1;0;0;0;0;1</DefaultValue>
					<Value>1;0;0;0;0;1;0;0;0;0;1;0;0;0;0;1</Value>
					<Modifiability>false</Modifiability>
				</Setting>
				<Setting>
					<TypeIdentifier>(0x007deef9, 0x2f3e95c6)</TypeIdentifier>
					<Name>Number of Output Channels</Name>
					<DefaultValue>4</DefaultValue>
					<Value>4</Value>
					<Modifiability>false</Modifiability>
				</Setting>
				<Setting>
					<TypeIdentifier>(0x007deef9, 0x2f3e95c6)</TypeIdentifier>
					<Name>Number of Input Channels</Name>
					<DefaultValue>4</DefaultValue>
					<Value>4</Value>
					<Modifiability>false</Modifiability>
				</Setting>
			</Settings>
			<Attributes>
				<Attribute>
					<Identifier>(0x1fa7a38f, 0x54edbe0b)</Identifier>
					<Value>-352</Value>
				</Attribute>
				<Attribute>
					<Identifier>(0x1fa963f5, 0x1a638cd4)</Identifier>
					<Value>65</Value>
				</Attribute>
				<Attribute>
					<Identifier>(0x207c9054, 0x3c841b63)</Identifier>
					<Value>704</Value>
				</Attribute>
				<Attribute>
					<Identifier>(0x30a4e5c9, 0x83502953)</Identifier>
					<Value></Value>
				</Attribute>
				<Attribute>
					<Identifier>(0x4e7b798a, 0x183beafb)</Identifier>
					<Value>(0x74d8d3ca, 0x2c7b1995)</Value>
				</Attribute>
				<Attribute>
					<Identifier>(0x527ad68d, 0x16d746a0)</Identifier>
					<Value></Value>
				</Attribute>
				<Attribute>
					<Identifier>(0x8d21ff41, 0xdf6afe7e)</Identifier>
					<Value>${Player_ScenarioDirectory}/${externalP300_paramFile}-spatial-filter.cfg</Value>
				</Attribute>
				<Attribute>
					<Identifier>(0xac367a9c, 0x2da95abe)</Identifier>
					<Value>68</Value>
				</Attribute>
				<Attribute>
					<Identifier>(0xad100179, 0xa3c984ab)</Identifier>
					<Value>163</Value>
				</Attribute>
				<Attribute>
					<Identifier>(0xc80ce8af, 0xf699f813)</Identifier>
					<Value>1</Value>
				</Attribute>
				<Attribute>
					<Identifier>(0xce18836a, 0x9c0eb403)</Identifier>
					<Value>3</Value>
				</Attribute>
				<Attribute>
					<Identifier>(0xcfad85b0, 0x7c6d841c)</Identifier>
					<Value>1</Value>
				</Attribute>
			</Attributes>
		</Box>
		<Box>
			<Identifier>(0x73d5aa3d, 0x20248d4b)</Identifier>
			<Name>Channel Selector</Name>
			<AlgorithmClassIdentifier>(0x361722e8, 0x311574e8)</AlgorithmClassIdentifier>
			<Inputs>
				<Input>
					<TypeIdentifier>(0x5ba36127, 0x195feae1)</TypeIdentifier>
					<Name>Input signal</Name>
				</Input>
			</Inputs>
			<Outputs>
				<Output>
					<TypeIdentifier>(0x5ba36127, 0x195feae1)</TypeIdentifier>
					<Name>Output signal</Name>
				</Output>
			</Outputs>
			<Settings>
				<Setting>
					<TypeIdentifier>(0x79a9edeb, 0x245d83fc)</TypeIdentifier>
					<Name>Channel List</Name>
					<DefaultValue>:</DefaultValue>
					<Value>${externalP300_Channels}</Value>
					<Modifiability>false</Modifiability>
				</Setting>
				<Setting>
					<TypeIdentifier>(0x3bcf9e67, 0x0c23994d)</TypeIdentifier>
					<Name>Action</Name>
					<DefaultValue>Select</DefaultValue>
					<Value>Select</Value>
					<Modifiability>false</Modifiability>
				</Setting>
				<Setting>
					<TypeIdentifier>(0x666f25e9, 0x3e5738d6)</TypeIdentifier>
					<Name>Channel Matching Method</Name>
					<DefaultValue>Smart</DefaultValue>
					<Value>Name</Value>
					<Modifiability>false</Modifiability>
				</Setting>
			</Settings>
			<Attributes>
				<Attribute>
					<Identifier>(0x1fa7a38f, 0x54edbe0b)</Identifier>
					<Value>-592.000000</Value>
				</Attribute>
				<Attribute>
					<Identifier>(0x1fa963f5, 0x1a638cd4)</Identifier>
					<Value>48</Value>
				</Attribute>
				<Attribute>
					<Identifier>(0x207c9054, 0x3c841b63)</Identifier>
					<Value>704.000000</Value>
				</Attribute>
				<Attribute>
					<Identifier>(0x30a4e5c9, 0x83502953)</Identifier>
					<Value></Value>
				</Attribute>
				<Attribute>
					<Identifier>(0x4e7b798a, 0x183beafb)</Identifier>
					<Value>(0x95781be1, 0xa38dce2d)</Value>
				</Attribute>
				<Attribute>
					<Identifier>(0x527ad68d, 0x16d746a0)</Identifier>
					<Value></Value>
				</Attribute>
				<Attribute>
					<Identifier>(0xad100179, 0xa3c984ab)</Identifier>
					<Value>132</Value>
				</Attribute>
				<Attribute>
					<Identifier>(0xc73e83ec, 0xf855c5bc)</Identifier>
					<Value>false</Value>
				</Attribute>
				<Attribute>
					<Identifier>(0xc80ce8af, 0xf699f813)</Identifier>
					<Value>1</Value>
				</Attribute>
				<Attribute>
					<Identifier>(0xce18836a, 0x9c0eb403)</Identifier>
					<Value>3</Value>
				</Attribute>
				<Attribute>
					<Identifier>(0xcfad85b0, 0x7c6d841c)</Identifier>
					<Value>1</Value>
				</Attribute>
			</Attributes>
		</Box>
	</Boxes>
	<Links>
		<Link>
			<Identifier>(0x01417ac1, 0x4e436224)</Identifier>
			<Source>
				<BoxIdentifier>(0x20ee2045, 0x1173220b)</BoxIdentifier>
				<BoxOutputIndex>0</BoxOutputIndex>
			</Source>
			<Target>
				<BoxIdentifier>(0x25a4953e, 0x48840e91)</BoxIdentifier>
				<BoxInputIndex>0</BoxInputIndex>
			</Target>
			<Attributes>
				<Attribute>
					<Identifier>(0x1b32c44c, 0x1905e0e9)</Identifier>
					<Value>-637</Value>
				</Attribute>
				<Attribute>
					<Identifier>(0x358ae8b5, 0x0f8bacd1)</Identifier>
					<Value>681</Value>
				</Attribute>
				<Attribute>
					<Identifier>(0x3f0a3b27, 0x570913d2)</Identifier>
					<Value>-573</Value>
				</Attribute>
				<Attribute>
					<Identifier>(0x6267b5c5, 0x676e3e42)</Identifier>
					<Value>193</Value>
				</Attribute>
			</Attributes>
		</Link>
		<Link>
			<Identifier>(0x03eb5ebf, 0x6a21a511)</Identifier>
			<Source>
				<BoxIdentifier>(0x3706b132, 0x00c4e50d)</BoxIdentifier>
				<BoxOutputIndex>0</BoxOutputIndex>
			</Source>
			<Target>
				<BoxIdentifier>(0x71eeb870, 0x43000732)</BoxIdentifier>
				<BoxInputIndex>0</BoxInputIndex>
			</Target>
			<Attributes>
				<Attribute>
					<Identifier>(0x1b32c44c, 0x1905e0e9)</Identifier>
					<Value>-394</Value>
				</Attribute>
				<Attribute>
					<Identifier>(0x358ae8b5, 0x0f8bacd1)</Identifier>
					<Value>704</Value>
				</Attribute>
				<Attribute>
					<Identifier>(0x3f0a3b27, 0x570913d2)</Identifier>
					<Value>-389</Value>
				</Attribute>
				<Attribute>
					<Identifier>(0x6267b5c5, 0x676e3e42)</Identifier>
					<Value>704</Value>
				</Attribute>
			</Attributes>
		</Link>
		<Link>
			<Identifier>(0x0ad0b9a8, 0x6659fd17)</Identifier>
			<Source>
				<BoxIdentifier>(0x0752e564, 0x1aa4aa27)</BoxIdentifier>
				<BoxOutputIndex>0</BoxOutputIndex>
			</Source>
			<Target>
				<BoxIdentifier>(0x5fd6c4c7, 0x21294a03)</BoxIdentifier>
				<BoxInputIndex>1</BoxInputIndex>
			</Target>
			<Attributes>
				<Attribute>
					<Identifier>(0x1b32c44c, 0x1905e0e9)</Identifier>
					<Value>-210</Value>
				</Attribute>
				<Attribute>
					<Identifier>(0x358ae8b5, 0x0f8bacd1)</Identifier>
					<Value>-64</Value>
				</Attribute>
				<Attribute>
					<Identifier>(0x3f0a3b27, 0x570913d2)</Identifier>
					<Value>-182</Value>
				</Attribute>
				<Attribute>
					<Identifier>(0x6267b5c5, 0x676e3e42)</Identifier>
					<Value>-89</Value>
				</Attribute>
			</Attributes>
		</Link>
		<Link>
			<Identifier>(0x0ba82d0c, 0x738c2d94)</Identifier>
			<Source>
				<BoxIdentifier>(0x5164de44, 0x71f34b55)</BoxIdentifier>
				<BoxOutputIndex>0</BoxOutputIndex>
			</Source>
			<Target>
				<BoxIdentifier>(0x1d5b71f3, 0x0427834b)</BoxIdentifier>
				<BoxInputIndex>1</BoxInputIndex>
			</Target>
			<Attributes>
				<Attribute>
					<Identifier>(0x1b32c44c, 0x1905e0e9)</Identifier>
					<Value>-194</Value>
				</Attribute>
				<Attribute>
					<Identifier>(0x358ae8b5, 0x0f8bacd1)</Identifier>
					<Value>129</Value>
				</Attribute>
				<Attribute>
					<Identifier>(0x3f0a3b27, 0x570913d2)</Identifier>
					<Value>-141</Value>
				</Attribute>
				<Attribute>
					<Identifier>(0x6267b5c5, 0x676e3e42)</Identifier>
					<Value>241</Value>
				</Attribute>
			</Attributes>
		</Link>
		<Link>
			<Identifier>(0x131db9d2, 0x686ce355)</Identifier>
			<Source>
				<BoxIdentifier>(0x4cab91da, 0x5e03f1e6)</BoxIdentifier>
				<BoxOutputIndex>0</BoxOutputIndex>
			</Source>
			<Target>
				<BoxIdentifier>(0x079b4a02, 0x73098828)</BoxIdentifier>
				<BoxInputIndex>0</BoxInputIndex>
			</Target>
			<Attributes>
				<Attribute>
					<Identifier>(0x1b32c44c, 0x1905e0e9)</Identifier>
					<Value>-338</Value>
				</Attribute>
				<Attribute>
					<Identifier>(0x358ae8b5, 0x0f8bacd1)</Identifier>
					<Value>1232</Value>
				</Attribute>
				<Attribute>
					<Identifier>(0x3f0a3b27, 0x570913d2)</Identifier>
					<Value>-148</Value>
				</Attribute>
				<Attribute>
					<Identifier>(0x6267b5c5, 0x676e3e42)</Identifier>
					<Value>1232</Value>
				</Attribute>
			</Attributes>
		</Link>
		<Link>
			<Identifier>(0x14018afa, 0x621272fe)</Identifier>
			<Source>
				<BoxIdentifier>(0x39f63dcd, 0x7ef5f905)</BoxIdentifier>
				<BoxOutputIndex>0</BoxOutputIndex>
			</Source>
			<Target>
				<BoxIdentifier>(0x5164de44, 0x71f34b55)</BoxIdentifier>
				<BoxInputIndex>0</BoxInputIndex>
			</Target>
			<Attributes>
				<Attribute>
					<Identifier>(0x1b32c44c, 0x1905e0e9)</Identifier>
					<Value>-282</Value>
				</Attribute>
				<Attribute>
					<Identifier>(0x358ae8b5, 0x0f8bacd1)</Identifier>
					<Value>136</Value>
				</Attribute>
				<Attribute>
					<Identifier>(0x3f0a3b27, 0x570913d2)</Identifier>
					<Value>-253</Value>
				</Attribute>
				<Attribute>
					<Identifier>(0x6267b5c5, 0x676e3e42)</Identifier>
					<Value>144</Value>
				</Attribute>
			</Attributes>
		</Link>
		<Link>
			<Identifier>(0x18919893, 0x24c29438)</Identifier>
			<Source>
				<BoxIdentifier>(0x5164de44, 0x71f34b55)</BoxIdentifier>
				<BoxOutputIndex>2</BoxOutputIndex>
			</Source>
			<Target>
				<BoxIdentifier>(0x1d5b71f3, 0x0427834b)</BoxIdentifier>
				<BoxInputIndex>2</BoxInputIndex>
			</Target>
			<Attributes>
				<Attribute>
					<Identifier>(0x1b32c44c, 0x1905e0e9)</Identifier>
					<Value>-194</Value>
				</Attribute>
				<Attribute>
					<Identifier>(0x358ae8b5, 0x0f8bacd1)</Identifier>
					<Value>159</Value>
				</Attribute>
				<Attribute>
					<Identifier>(0x3f0a3b27, 0x570913d2)</Identifier>
					<Value>-141</Value>
				</Attribute>
				<Attribute>
					<Identifier>(0x6267b5c5, 0x676e3e42)</Identifier>
					<Value>256</Value>
				</Attribute>
			</Attributes>
		</Link>
		<Link>
			<Identifier>(0x1a12b459, 0x6921c9c3)</Identifier>
			<Source>
				<BoxIdentifier>(0x25a4953e, 0x48840e91)</BoxIdentifier>
				<BoxOutputIndex>2</BoxOutputIndex>
			</Source>
			<Target>
				<BoxIdentifier>(0x1d5b71f3, 0x0427834b)</BoxIdentifier>
				<BoxInputIndex>0</BoxInputIndex>
			</Target>
			<Attributes>
				<Attribute>
					<Identifier>(0x1b32c44c, 0x1905e0e9)</Identifier>
					<Value>-514</Value>
				</Attribute>
				<Attribute>
					<Identifier>(0x358ae8b5, 0x0f8bacd1)</Identifier>
					<Value>223</Value>
				</Attribute>
				<Attribute>
					<Identifier>(0x3f0a3b27, 0x570913d2)</Identifier>
					<Value>-141</Value>
				</Attribute>
				<Attribute>
					<Identifier>(0x6267b5c5, 0x676e3e42)</Identifier>
					<Value>226</Value>
				</Attribute>
			</Attributes>
		</Link>
		<Link>
			<Identifier>(0x24fbf84a, 0x40950fd0)</Identifier>
			<Source>
				<BoxIdentifier>(0x2c59bb68, 0x607f56d9)</BoxIdentifier>
				<BoxOutputIndex>0</BoxOutputIndex>
			</Source>
			<Target>
				<BoxIdentifier>(0x641cd641, 0x7b1a71b3)</BoxIdentifier>
				<BoxInputIndex>0</BoxInputIndex>
			</Target>
			<Attributes>
				<Attribute>
					<Identifier>(0x1b32c44c, 0x1905e0e9)</Identifier>
					<Value>-250</Value>
				</Attribute>
				<Attribute>
					<Identifier>(0x358ae8b5, 0x0f8bacd1)</Identifier>
					<Value>696</Value>
				</Attribute>
				<Attribute>
					<Identifier>(0x3f0a3b27, 0x570913d2)</Identifier>
					<Value>-237</Value>
				</Attribute>
				<Attribute>
					<Identifier>(0x6267b5c5, 0x676e3e42)</Identifier>
					<Value>704</Value>
				</Attribute>
			</Attributes>
		</Link>
		<Link>
			<Identifier>(0x29ffcf90, 0x6293ec84)</Identifier>
			<Source>
				<BoxIdentifier>(0x0099cd55, 0x45b5fc65)</BoxIdentifier>
				<BoxOutputIndex>2</BoxOutputIndex>
			</Source>
			<Target>
				<BoxIdentifier>(0x1d5b71f3, 0x0427834b)</BoxIdentifier>
				<BoxInputIndex>4</BoxInputIndex>
			</Target>
			<Attributes>
				<Attribute>
					<Identifier>(0x1b32c44c, 0x1905e0e9)</Identifier>
					<Value>-205</Value>
				</Attribute>
				<Attribute>
					<Identifier>(0x358ae8b5, 0x0f8bacd1)</Identifier>
					<Value>399</Value>
				</Attribute>
				<Attribute>
					<Identifier>(0x3f0a3b27, 0x570913d2)</Identifier>
					<Value>-141</Value>
				</Attribute>
				<Attribute>
					<Identifier>(0x6267b5c5, 0x676e3e42)</Identifier>
					<Value>286</Value>
				</Attribute>
			</Attributes>
		</Link>
		<Link>
			<Identifier>(0x2aab4033, 0x44d14a73)</Identifier>
			<Source>
				<BoxIdentifier>(0x73d5aa3d, 0x20248d4b)</BoxIdentifier>
				<BoxOutputIndex>0</BoxOutputIndex>
			</Source>
			<Target>
				<BoxIdentifier>(0x25a4953e, 0x48840e91)</BoxIdentifier>
				<BoxInputIndex>1</BoxInputIndex>
			</Target>
			<Attributes>
				<Attribute>
					<Identifier>(0x1b32c44c, 0x1905e0e9)</Identifier>
					<Value>-562</Value>
				</Attribute>
				<Attribute>
					<Identifier>(0x358ae8b5, 0x0f8bacd1)</Identifier>
					<Value>704</Value>
				</Attribute>
				<Attribute>
					<Identifier>(0x3f0a3b27, 0x570913d2)</Identifier>
					<Value>-573</Value>
				</Attribute>
				<Attribute>
					<Identifier>(0x6267b5c5, 0x676e3e42)</Identifier>
					<Value>208</Value>
				</Attribute>
			</Attributes>
		</Link>
		<Link>
			<Identifier>(0x2b139d49, 0x795d979f)</Identifier>
			<Source>
				<BoxIdentifier>(0x25a4953e, 0x48840e91)</BoxIdentifier>
				<BoxOutputIndex>2</BoxOutputIndex>
			</Source>
			<Target>
				<BoxIdentifier>(0x39f63dcd, 0x7ef5f905)</BoxIdentifier>
				<BoxInputIndex>1</BoxInputIndex>
			</Target>
			<Attributes>
				<Attribute>
					<Identifier>(0x1b32c44c, 0x1905e0e9)</Identifier>
					<Value>-514</Value>
				</Attribute>
				<Attribute>
					<Identifier>(0x358ae8b5, 0x0f8bacd1)</Identifier>
					<Value>223</Value>
				</Attribute>
				<Attribute>
					<Identifier>(0x3f0a3b27, 0x570913d2)</Identifier>
					<Value>-324</Value>
				</Attribute>
				<Attribute>
					<Identifier>(0x6267b5c5, 0x676e3e42)</Identifier>
					<Value>151</Value>
				</Attribute>
			</Attributes>
		</Link>
		<Link>
			<Identifier>(0x2c881028, 0x0d2ab3a5)</Identifier>
			<Source>
				<BoxIdentifier>(0x71eeb870, 0x43000732)</BoxIdentifier>
				<BoxOutputIndex>0</BoxOutputIndex>
			</Source>
			<Target>
				<BoxIdentifier>(0x2c59bb68, 0x607f56d9)</BoxIdentifier>
				<BoxInputIndex>0</BoxInputIndex>
			</Target>
			<Attributes>
				<Attribute>
					<Identifier>(0x1b32c44c, 0x1905e0e9)</Identifier>
					<Value>-313</Value>
				</Attribute>
				<Attribute>
					<Identifier>(0x358ae8b5, 0x0f8bacd1)</Identifier>
					<Value>704</Value>
				</Attribute>
				<Attribute>
					<Identifier>(0x3f0a3b27, 0x570913d2)</Identifier>
					<Value>-292</Value>
				</Attribute>
				<Attribute>
					<Identifier>(0x6267b5c5, 0x676e3e42)</Identifier>
					<Value>696</Value>
				</Attribute>
			</Attributes>
		</Link>
		<Link>
			<Identifier>(0x2f534be3, 0x4c01bd90)</Identifier>
			<Source>
				<BoxIdentifier>(0x0099cd55, 0x45b5fc65)</BoxIdentifier>
				<BoxOutputIndex>0</BoxOutputIndex>
			</Source>
			<Target>
				<BoxIdentifier>(0x1d5b71f3, 0x0427834b)</BoxIdentifier>
				<BoxInputIndex>3</BoxInputIndex>
			</Target>
			<Attributes>
				<Attribute>
					<Identifier>(0x1b32c44c, 0x1905e0e9)</Identifier>
					<Value>-205</Value>
				</Attribute>
				<Attribute>
					<Identifier>(0x358ae8b5, 0x0f8bacd1)</Identifier>
					<Value>369</Value>
				</Attribute>
				<Attribute>
					<Identifier>(0x3f0a3b27, 0x570913d2)</Identifier>
					<Value>-141</Value>
				</Attribute>
				<Attribute>
					<Identifier>(0x6267b5c5, 0x676e3e42)</Identifier>
					<Value>271</Value>
				</Attribute>
			</Attributes>
		</Link>
		<Link>
			<Identifier>(0x2fb62fb4, 0x57082224)</Identifier>
			<Source>
				<BoxIdentifier>(0x1b10b921, 0x7b3cc877)</BoxIdentifier>
				<BoxOutputIndex>0</BoxOutputIndex>
			</Source>
			<Target>
				<BoxIdentifier>(0x5fd6c4c7, 0x21294a03)</BoxIdentifier>
				<BoxInputIndex>0</BoxInputIndex>
			</Target>
			<Attributes>
				<Attribute>
					<Identifier>(0x1b32c44c, 0x1905e0e9)</Identifier>
					<Value>-290</Value>
				</Attribute>
				<Attribute>
					<Identifier>(0x358ae8b5, 0x0f8bacd1)</Identifier>
					<Value>-208</Value>
				</Attribute>
				<Attribute>
					<Identifier>(0x3f0a3b27, 0x570913d2)</Identifier>
					<Value>-182</Value>
				</Attribute>
				<Attribute>
					<Identifier>(0x6267b5c5, 0x676e3e42)</Identifier>
					<Value>-104</Value>
				</Attribute>
			</Attributes>
		</Link>
		<Link>
			<Identifier>(0x38b6b3a0, 0x0a805105)</Identifier>
			<Source>
				<BoxIdentifier>(0x20ee2045, 0x1173220b)</BoxIdentifier>
				<BoxOutputIndex>1</BoxOutputIndex>
			</Source>
			<Target>
				<BoxIdentifier>(0x73d5aa3d, 0x20248d4b)</BoxIdentifier>
				<BoxInputIndex>0</BoxInputIndex>
			</Target>
			<Attributes>
				<Attribute>
					<Identifier>(0x1b32c44c, 0x1905e0e9)</Identifier>
					<Value>-637</Value>
				</Attribute>
				<Attribute>
					<Identifier>(0x358ae8b5, 0x0f8bacd1)</Identifier>
					<Value>696</Value>
				</Attribute>
				<Attribute>
					<Identifier>(0x3f0a3b27, 0x570913d2)</Identifier>
					<Value>-621</Value>
				</Attribute>
				<Attribute>
					<Identifier>(0x6267b5c5, 0x676e3e42)</Identifier>
					<Value>704</Value>
				</Attribute>
			</Attributes>
		</Link>
		<Link>
			<Identifier>(0x38e2ec4f, 0x18e2c619)</Identifier>
			<Source>
				<BoxIdentifier>(0x20ee2045, 0x1173220b)</BoxIdentifier>
				<BoxOutputIndex>2</BoxOutputIndex>
			</Source>
			<Target>
				<BoxIdentifier>(0x4cab91da, 0x5e03f1e6)</BoxIdentifier>
				<BoxInputIndex>0</BoxInputIndex>
			</Target>
			<Attributes>
				<Attribute>
					<Identifier>(0x1b32c44c, 0x1905e0e9)</Identifier>
					<Value>-637</Value>
				</Attribute>
				<Attribute>
					<Identifier>(0x358ae8b5, 0x0f8bacd1)</Identifier>
					<Value>711</Value>
				</Attribute>
				<Attribute>
					<Identifier>(0x3f0a3b27, 0x570913d2)</Identifier>
					<Value>-397</Value>
				</Attribute>
				<Attribute>
					<Identifier>(0x6267b5c5, 0x676e3e42)</Identifier>
					<Value>1232</Value>
				</Attribute>
			</Attributes>
		</Link>
		<Link>
			<Identifier>(0x3e76898f, 0x6e5b259c)</Identifier>
			<Source>
				<BoxIdentifier>(0x5905c5f5, 0x32d562d1)</BoxIdentifier>
				<BoxOutputIndex>0</BoxOutputIndex>
			</Source>
			<Target>
				<BoxIdentifier>(0x4cddfdbe, 0x37b0e8b9)</BoxIdentifier>
				<BoxInputIndex>0</BoxInputIndex>
			</Target>
			<Attributes>
				<Attribute>
					<Identifier>(0x1b32c44c, 0x1905e0e9)</Identifier>
					<Value>-338</Value>
				</Attribute>
				<Attribute>
					<Identifier>(0x358ae8b5, 0x0f8bacd1)</Identifier>
					<Value>272</Value>
				</Attribute>
				<Attribute>
					<Identifier>(0x3f0a3b27, 0x570913d2)</Identifier>
					<Value>-324</Value>
				</Attribute>
				<Attribute>
					<Identifier>(0x6267b5c5, 0x676e3e42)</Identifier>
					<Value>424</Value>
				</Attribute>
			</Attributes>
		</Link>
		<Link>
			<Identifier>(0x436a4dae, 0x68363833)</Identifier>
			<Source>
				<BoxIdentifier>(0x563ffbad, 0x25b157d0)</BoxIdentifier>
				<BoxOutputIndex>0</BoxOutputIndex>
			</Source>
			<Target>
				<BoxIdentifier>(0x3706b132, 0x00c4e50d)</BoxIdentifier>
				<BoxInputIndex>0</BoxInputIndex>
			</Target>
			<Attributes>
				<Attribute>
					<Identifier>(0x1b32c44c, 0x1905e0e9)</Identifier>
					<Value>-450</Value>
				</Attribute>
				<Attribute>
					<Identifier>(0x358ae8b5, 0x0f8bacd1)</Identifier>
					<Value>704</Value>
				</Attribute>
				<Attribute>
					<Identifier>(0x3f0a3b27, 0x570913d2)</Identifier>
					<Value>-436</Value>
				</Attribute>
				<Attribute>
					<Identifier>(0x6267b5c5, 0x676e3e42)</Identifier>
					<Value>704</Value>
				</Attribute>
			</Attributes>
		</Link>
		<Link>
			<Identifier>(0x4cc6a29b, 0x3d6d25b6)</Identifier>
			<Source>
				<BoxIdentifier>(0x25a4953e, 0x48840e91)</BoxIdentifier>
				<BoxOutputIndex>1</BoxOutputIndex>
			</Source>
			<Target>
				<BoxIdentifier>(0x10d954b5, 0x7150b4cf)</BoxIdentifier>
				<BoxInputIndex>1</BoxInputIndex>
			</Target>
			<Attributes>
				<Attribute>
					<Identifier>(0x1b32c44c, 0x1905e0e9)</Identifier>
					<Value>-514</Value>
				</Attribute>
				<Attribute>
					<Identifier>(0x358ae8b5, 0x0f8bacd1)</Identifier>
					<Value>208</Value>
				</Attribute>
				<Attribute>
					<Identifier>(0x3f0a3b27, 0x570913d2)</Identifier>
					<Value>-477</Value>
				</Attribute>
				<Attribute>
					<Identifier>(0x6267b5c5, 0x676e3e42)</Identifier>
					<Value>-48</Value>
				</Attribute>
			</Attributes>
		</Link>
		<Link>
			<Identifier>(0x4e903548, 0x31ab2644)</Identifier>
			<Source>
				<BoxIdentifier>(0x71eeb870, 0x43000732)</BoxIdentifier>
				<BoxOutputIndex>0</BoxOutputIndex>
			</Source>
			<Target>
				<BoxIdentifier>(0x5905c5f5, 0x32d562d1)</BoxIdentifier>
				<BoxInputIndex>0</BoxInputIndex>
			</Target>
			<Attributes>
				<Attribute>
					<Identifier>(0x1b32c44c, 0x1905e0e9)</Identifier>
					<Value>-313</Value>
				</Attribute>
				<Attribute>
					<Identifier>(0x358ae8b5, 0x0f8bacd1)</Identifier>
					<Value>704</Value>
				</Attribute>
				<Attribute>
					<Identifier>(0x3f0a3b27, 0x570913d2)</Identifier>
					<Value>-397</Value>
				</Attribute>
				<Attribute>
					<Identifier>(0x6267b5c5, 0x676e3e42)</Identifier>
					<Value>272</Value>
				</Attribute>
			</Attributes>
		</Link>
		<Link>
			<Identifier>(0x559423d0, 0x5a8f29b7)</Identifier>
			<Source>
				<BoxIdentifier>(0x25a4953e, 0x48840e91)</BoxIdentifier>
				<BoxOutputIndex>0</BoxOutputIndex>
			</Source>
			<Target>
				<BoxIdentifier>(0x10d954b5, 0x7150b4cf)</BoxIdentifier>
				<BoxInputIndex>0</BoxInputIndex>
			</Target>
			<Attributes>
				<Attribute>
					<Identifier>(0x1b32c44c, 0x1905e0e9)</Identifier>
					<Value>-514</Value>
				</Attribute>
				<Attribute>
					<Identifier>(0x358ae8b5, 0x0f8bacd1)</Identifier>
					<Value>193</Value>
				</Attribute>
				<Attribute>
					<Identifier>(0x3f0a3b27, 0x570913d2)</Identifier>
					<Value>-477</Value>
				</Attribute>
				<Attribute>
					<Identifier>(0x6267b5c5, 0x676e3e42)</Identifier>
					<Value>-63</Value>
				</Attribute>
			</Attributes>
		</Link>
		<Link>
			<Identifier>(0x56201a16, 0x7381b0d4)</Identifier>
			<Source>
				<BoxIdentifier>(0x641cd641, 0x7b1a71b3)</BoxIdentifier>
				<BoxOutputIndex>0</BoxOutputIndex>
			</Source>
			<Target>
				<BoxIdentifier>(0x329c6c0d, 0x3ea1fb35)</BoxIdentifier>
				<BoxInputIndex>0</BoxInputIndex>
			</Target>
			<Attributes>
				<Attribute>
					<Identifier>(0x1b32c44c, 0x1905e0e9)</Identifier>
					<Value>-178</Value>
				</Attribute>
				<Attribute>
					<Identifier>(0x358ae8b5, 0x0f8bacd1)</Identifier>
					<Value>704</Value>
				</Attribute>
				<Attribute>
					<Identifier>(0x3f0a3b27, 0x570913d2)</Identifier>
					<Value>-148</Value>
				</Attribute>
				<Attribute>
					<Identifier>(0x6267b5c5, 0x676e3e42)</Identifier>
					<Value>704</Value>
				</Attribute>
			</Attributes>
		</Link>
		<Link>
			<Identifier>(0x56a3caf7, 0x40899b23)</Identifier>
			<Source>
				<BoxIdentifier>(0x5905c5f5, 0x32d562d1)</BoxIdentifier>
				<BoxOutputIndex>0</BoxOutputIndex>
			</Source>
			<Target>
				<BoxIdentifier>(0x39f63dcd, 0x7ef5f905)</BoxIdentifier>
				<BoxInputIndex>0</BoxInputIndex>
			</Target>
			<Attributes>
				<Attribute>
					<Identifier>(0x1b32c44c, 0x1905e0e9)</Identifier>
					<Value>-338</Value>
				</Attribute>
				<Attribute>
					<Identifier>(0x358ae8b5, 0x0f8bacd1)</Identifier>
					<Value>272</Value>
				</Attribute>
				<Attribute>
					<Identifier>(0x3f0a3b27, 0x570913d2)</Identifier>
					<Value>-324</Value>
				</Attribute>
				<Attribute>
					<Identifier>(0x6267b5c5, 0x676e3e42)</Identifier>
					<Value>136</Value>
				</Attribute>
			</Attributes>
		</Link>
		<Link>
			<Identifier>(0x61887327, 0x7ae0553b)</Identifier>
			<Source>
				<BoxIdentifier>(0x25a4953e, 0x48840e91)</BoxIdentifier>
				<BoxOutputIndex>2</BoxOutputIndex>
			</Source>
			<Target>
				<BoxIdentifier>(0x10d954b5, 0x7150b4cf)</BoxIdentifier>
				<BoxInputIndex>2</BoxInputIndex>
			</Target>
			<Attributes>
				<Attribute>
					<Identifier>(0x1b32c44c, 0x1905e0e9)</Identifier>
					<Value>-514</Value>
				</Attribute>
				<Attribute>
					<Identifier>(0x358ae8b5, 0x0f8bacd1)</Identifier>
					<Value>223</Value>
				</Attribute>
				<Attribute>
					<Identifier>(0x3f0a3b27, 0x570913d2)</Identifier>
					<Value>-477</Value>
				</Attribute>
				<Attribute>
					<Identifier>(0x6267b5c5, 0x676e3e42)</Identifier>
					<Value>-33</Value>
				</Attribute>
			</Attributes>
		</Link>
		<Link>
			<Identifier>(0x64e483a7, 0x4e3b0757)</Identifier>
			<Source>
				<BoxIdentifier>(0x25a4953e, 0x48840e91)</BoxIdentifier>
				<BoxOutputIndex>1</BoxOutputIndex>
			</Source>
			<Target>
				<BoxIdentifier>(0x563ffbad, 0x25b157d0)</BoxIdentifier>
				<BoxInputIndex>0</BoxInputIndex>
			</Target>
			<Attributes>
				<Attribute>
					<Identifier>(0x1b32c44c, 0x1905e0e9)</Identifier>
					<Value>-514</Value>
				</Attribute>
				<Attribute>
					<Identifier>(0x358ae8b5, 0x0f8bacd1)</Identifier>
					<Value>208</Value>
				</Attribute>
				<Attribute>
					<Identifier>(0x3f0a3b27, 0x570913d2)</Identifier>
					<Value>-509</Value>
				</Attribute>
				<Attribute>
					<Identifier>(0x6267b5c5, 0x676e3e42)</Identifier>
					<Value>704</Value>
				</Attribute>
			</Attributes>
		</Link>
		<Link>
			<Identifier>(0x67c29b68, 0x0562457b)</Identifier>
			<Source>
				<BoxIdentifier>(0x25a4953e, 0x48840e91)</BoxIdentifier>
				<BoxOutputIndex>1</BoxOutputIndex>
			</Source>
			<Target>
				<BoxIdentifier>(0x1b10b921, 0x7b3cc877)</BoxIdentifier>
				<BoxInputIndex>0</BoxInputIndex>
			</Target>
			<Attributes>
				<Attribute>
					<Identifier>(0x1b32c44c, 0x1905e0e9)</Identifier>
					<Value>-514</Value>
				</Attribute>
				<Attribute>
					<Identifier>(0x358ae8b5, 0x0f8bacd1)</Identifier>
					<Value>208</Value>
				</Attribute>
				<Attribute>
					<Identifier>(0x3f0a3b27, 0x570913d2)</Identifier>
					<Value>-349</Value>
				</Attribute>
				<Attribute>
					<Identifier>(0x6267b5c5, 0x676e3e42)</Identifier>
					<Value>-208</Value>
				</Attribute>
			</Attributes>
		</Link>
		<Link>
			<Identifier>(0x688442e9, 0x3e029716)</Identifier>
			<Source>
				<BoxIdentifier>(0x25a4953e, 0x48840e91)</BoxIdentifier>
				<BoxOutputIndex>2</BoxOutputIndex>
			</Source>
			<Target>
				<BoxIdentifier>(0x0752e564, 0x1aa4aa27)</BoxIdentifier>
				<BoxInputIndex>0</BoxInputIndex>
			</Target>
			<Attributes>
				<Attribute>
					<Identifier>(0x1b32c44c, 0x1905e0e9)</Identifier>
					<Value>-514</Value>
				</Attribute>
				<Attribute>
					<Identifier>(0x358ae8b5, 0x0f8bacd1)</Identifier>
					<Value>223</Value>
				</Attribute>
				<Attribute>
					<Identifier>(0x3f0a3b27, 0x570913d2)</Identifier>
					<Value>-269</Value>
				</Attribute>
				<Attribute>
					<Identifier>(0x6267b5c5, 0x676e3e42)</Identifier>
					<Value>-64</Value>
				</Attribute>
			</Attributes>
		</Link>
		<Link>
			<Identifier>(0x68dfbfac, 0x7decee6e)</Identifier>
			<Source>
				<BoxIdentifier>(0x329c6c0d, 0x3ea1fb35)</BoxIdentifier>
				<BoxOutputIndex>1</BoxOutputIndex>
			</Source>
			<Target>
				<BoxIdentifier>(0x6c153974, 0x133ff47d)</BoxIdentifier>
				<BoxInputIndex>0</BoxInputIndex>
			</Target>
			<Attributes>
				<Attribute>
					<Identifier>(0x1b32c44c, 0x1905e0e9)</Identifier>
					<Value>-106</Value>
				</Attribute>
				<Attribute>
					<Identifier>(0x358ae8b5, 0x0f8bacd1)</Identifier>
					<Value>711</Value>
				</Attribute>
				<Attribute>
					<Identifier>(0x3f0a3b27, 0x570913d2)</Identifier>
					<Value>-85</Value>
				</Attribute>
				<Attribute>
					<Identifier>(0x6267b5c5, 0x676e3e42)</Identifier>
					<Value>704</Value>
				</Attribute>
			</Attributes>
		</Link>
		<Link>
			<Identifier>(0x6dcf28cf, 0x4a0cb611)</Identifier>
			<Source>
				<BoxIdentifier>(0x20ee2045, 0x1173220b)</BoxIdentifier>
				<BoxOutputIndex>2</BoxOutputIndex>
			</Source>
			<Target>
				<BoxIdentifier>(0x25a4953e, 0x48840e91)</BoxIdentifier>
				<BoxInputIndex>2</BoxInputIndex>
			</Target>
			<Attributes>
				<Attribute>
					<Identifier>(0x1b32c44c, 0x1905e0e9)</Identifier>
					<Value>-637</Value>
				</Attribute>
				<Attribute>
					<Identifier>(0x358ae8b5, 0x0f8bacd1)</Identifier>
					<Value>711</Value>
				</Attribute>
				<Attribute>
					<Identifier>(0x3f0a3b27, 0x570913d2)</Identifier>
					<Value>-573</Value>
				</Attribute>
				<Attribute>
					<Identifier>(0x6267b5c5, 0x676e3e42)</Identifier>
					<Value>223</Value>
				</Attribute>
			</Attributes>
		</Link>
		<Link>
			<Identifier>(0x6f3d26a2, 0x3f838aa4)</Identifier>
			<Source>
				<BoxIdentifier>(0x4cddfdbe, 0x37b0e8b9)</BoxIdentifier>
				<BoxOutputIndex>0</BoxOutputIndex>
			</Source>
			<Target>
				<BoxIdentifier>(0x0099cd55, 0x45b5fc65)</BoxIdentifier>
				<BoxInputIndex>0</BoxInputIndex>
			</Target>
			<Attributes>
				<Attribute>
					<Identifier>(0x1b32c44c, 0x1905e0e9)</Identifier>
					<Value>-282</Value>
				</Attribute>
				<Attribute>
					<Identifier>(0x358ae8b5, 0x0f8bacd1)</Identifier>
					<Value>424</Value>
				</Attribute>
				<Attribute>
					<Identifier>(0x3f0a3b27, 0x570913d2)</Identifier>
					<Value>-264</Value>
				</Attribute>
				<Attribute>
					<Identifier>(0x6267b5c5, 0x676e3e42)</Identifier>
					<Value>384</Value>
				</Attribute>
			</Attributes>
		</Link>
		<Link>
			<Identifier>(0x72403612, 0x35a7fc9d)</Identifier>
			<Source>
				<BoxIdentifier>(0x25a4953e, 0x48840e91)</BoxIdentifier>
				<BoxOutputIndex>2</BoxOutputIndex>
			</Source>
			<Target>
				<BoxIdentifier>(0x2c59bb68, 0x607f56d9)</BoxIdentifier>
				<BoxInputIndex>1</BoxInputIndex>
			</Target>
			<Attributes>
				<Attribute>
					<Identifier>(0x1b32c44c, 0x1905e0e9)</Identifier>
					<Value>-514</Value>
				</Attribute>
				<Attribute>
					<Identifier>(0x358ae8b5, 0x0f8bacd1)</Identifier>
					<Value>223</Value>
				</Attribute>
				<Attribute>
					<Identifier>(0x3f0a3b27, 0x570913d2)</Identifier>
					<Value>-292</Value>
				</Attribute>
				<Attribute>
					<Identifier>(0x6267b5c5, 0x676e3e42)</Identifier>
					<Value>711</Value>
				</Attribute>
			</Attributes>
		</Link>
		<Link>
			<Identifier>(0x7f1dfef9, 0x7032a511)</Identifier>
			<Source>
				<BoxIdentifier>(0x25a4953e, 0x48840e91)</BoxIdentifier>
				<BoxOutputIndex>2</BoxOutputIndex>
			</Source>
			<Target>
				<BoxIdentifier>(0x4cddfdbe, 0x37b0e8b9)</BoxIdentifier>
				<BoxInputIndex>1</BoxInputIndex>
			</Target>
			<Attributes>
				<Attribute>
					<Identifier>(0x1b32c44c, 0x1905e0e9)</Identifier>
					<Value>-514</Value>
				</Attribute>
				<Attribute>
					<Identifier>(0x358ae8b5, 0x0f8bacd1)</Identifier>
					<Value>223</Value>
				</Attribute>
				<Attribute>
					<Identifier>(0x3f0a3b27, 0x570913d2)</Identifier>
					<Value>-324</Value>
				</Attribute>
				<Attribute>
					<Identifier>(0x6267b5c5, 0x676e3e42)</Identifier>
					<Value>439</Value>
				</Attribute>
			</Attributes>
		</Link>
	</Links>
	<MessageLinks></MessageLinks>
	<Comments>
		<Comment>
			<Identifier>(0x0252bb13, 0x21c1c92a)</Identifier>
			<Text>See more detailed explanation of the p300 protocol on
http://openvibe.inria.fr/p300-with-external-stimulator-tutorial/</Text>
			<Attributes>
				<Attribute>
					<Identifier>(0x473d9a43, 0x97fc0a97)</Identifier>
					<Value>112.000000</Value>
				</Attribute>
				<Attribute>
					<Identifier>(0x7234b86b, 0x2b8651a5)</Identifier>
					<Value>-744.000000</Value>
				</Attribute>
			</Attributes>
		</Comment>
		<Comment>
			<Identifier>(0x24439293, 0x316d9e77)</Identifier>
			<Text>When you press 'escape' in the external application,
it will stop it. The application send back through the 
tagging system the End of experiment stimulis (182) 
that stops the scenario.</Text>
			<Attributes>
				<Attribute>
					<Identifier>(0x473d9a43, 0x97fc0a97)</Identifier>
					<Value>1136</Value>
				</Attribute>
				<Attribute>
					<Identifier>(0x7234b86b, 0x2b8651a5)</Identifier>
					<Value>-496</Value>
				</Attribute>
			</Attributes>
		</Comment>
		<Comment>
			<Identifier>(0x3d97f439, 0x40ac6af3)</Identifier>
			<Text>This is the default scenario that should be used with
 the external p300 stimulator. It can be used for both calibration (
in this case dummy spatial filters and classifer
are used), for copy and free spelling. A static classifier
is used but it can stop early.</Text>
			<Attributes>
				<Attribute>
					<Identifier>(0x473d9a43, 0x97fc0a97)</Identifier>
					<Value>592.000000</Value>
				</Attribute>
				<Attribute>
					<Identifier>(0x7234b86b, 0x2b8651a5)</Identifier>
					<Value>-752.000000</Value>
				</Attribute>
			</Attributes>
		</Comment>
		<Comment>
			<Identifier>(0x60d0f83c, 0x086068d5)</Identifier>
			<Text>This part of the scenario is responsible for showing 
the signals and the target versus non-target figures 
with confidence bound</Text>
			<Attributes>
				<Attribute>
					<Identifier>(0x473d9a43, 0x97fc0a97)</Identifier>
					<Value>16</Value>
				</Attribute>
				<Attribute>
					<Identifier>(0x7234b86b, 0x2b8651a5)</Identifier>
					<Value>-640</Value>
				</Attribute>
			</Attributes>
		</Comment>
		<Comment>
			<Identifier>(0x73ce6d33, 0x6c92a9db)</Identifier>
			<Text>Temporal filtering and spatial 
filtering is done before epoching. 
Epochs are extracted based on 
the stimulation
identifier 195 (corresponding to a flash). 
The classifier outputs the 
probability for each flash.
This result is written in shared memory 
which is read by the p300 stimulator.
This probability is then combined in the 
evidence accumulator module of the external 
application with the info about the symbols 
being flashed. 
It then computes the probabilities for each 
symbol and outputs the most probable one 
when a certain threshold is reached.
</Text>
			<Attributes>
				<Attribute>
					<Identifier>(0x473d9a43, 0x97fc0a97)</Identifier>
					<Value>992</Value>
				</Attribute>
				<Attribute>
					<Identifier>(0x7234b86b, 0x2b8651a5)</Identifier>
					<Value>-240</Value>
				</Attribute>
			</Attributes>
		</Comment>
	</Comments>
	<VisualisationTree>
		<VisualisationWidget>
			<Identifier>(0x24600676, 0x41b79646)</Identifier>
			<Name>Default window</Name>
			<Type>1</Type>
			<ParentIdentifier>(0xffffffff, 0xffffffff)</ParentIdentifier>
			<BoxIdentifier>(0xffffffff, 0xffffffff)</BoxIdentifier>
			<NumChildren>1</NumChildren>
			<Attributes>
				<Attribute>
					<Identifier>(0x4c90d4ad, 0x7a2554ec)</Identifier>
					<Value>320</Value>
				</Attribute>
				<Attribute>
					<Identifier>(0x7b814cca, 0x271df6dd)</Identifier>
					<Value>474</Value>
				</Attribute>
			</Attributes>
		</VisualisationWidget>
		<VisualisationWidget>
			<Identifier>(0x3235c762, 0x21b25f0c)</Identifier>
			<Type>3</Type>
			<ParentIdentifier>(0xffffffff, 0xffffffff)</ParentIdentifier>
			<BoxIdentifier>(0x1b10b921, 0x7b3cc877)</BoxIdentifier>
			<NumChildren>0</NumChildren>
		</VisualisationWidget>
		<VisualisationWidget>
			<Identifier>(0x332c700d, 0x49c8e40d)</Identifier>
			<Type>3</Type>
			<ParentIdentifier>(0xffffffff, 0xffffffff)</ParentIdentifier>
			<BoxIdentifier>(0x0752e564, 0x1aa4aa27)</BoxIdentifier>
			<NumChildren>0</NumChildren>
		</VisualisationWidget>
		<VisualisationWidget>
			<Identifier>(0x35394719, 0x429ff288)</Identifier>
			<Type>3</Type>
			<ParentIdentifier>(0xffffffff, 0xffffffff)</ParentIdentifier>
			<BoxIdentifier>(0x20ee2045, 0x1173220b)</BoxIdentifier>
			<NumChildren>0</NumChildren>
		</VisualisationWidget>
		<VisualisationWidget>
			<Identifier>(0x38e7b649, 0x2f2962ca)</Identifier>
			<Type>3</Type>
			<ParentIdentifier>(0xffffffff, 0xffffffff)</ParentIdentifier>
			<BoxIdentifier>(0x4cddfdbe, 0x37b0e8b9)</BoxIdentifier>
			<NumChildren>0</NumChildren>
		</VisualisationWidget>
		<VisualisationWidget>
			<Identifier>(0x3eb493c9, 0x7a80208d)</Identifier>
			<Type>3</Type>
			<ParentIdentifier>(0xffffffff, 0xffffffff)</ParentIdentifier>
			<BoxIdentifier>(0x39f63dcd, 0x7ef5f905)</BoxIdentifier>
			<NumChildren>0</NumChildren>
		</VisualisationWidget>
		<VisualisationWidget>
			<Identifier>(0x4029ebe5, 0x464a29df)</Identifier>
			<Type>3</Type>
			<ParentIdentifier>(0xffffffff, 0xffffffff)</ParentIdentifier>
			<BoxIdentifier>(0x71eeb870, 0x43000732)</BoxIdentifier>
			<NumChildren>0</NumChildren>
		</VisualisationWidget>
		<VisualisationWidget>
			<Identifier>(0x412a7f19, 0x2004f031)</Identifier>
			<Type>3</Type>
			<ParentIdentifier>(0xffffffff, 0xffffffff)</ParentIdentifier>
			<BoxIdentifier>(0x10d954b5, 0x7150b4cf)</BoxIdentifier>
			<NumChildren>0</NumChildren>
		</VisualisationWidget>
		<VisualisationWidget>
			<Identifier>(0x4f776034, 0x090c972d)</Identifier>
			<Type>3</Type>
			<ParentIdentifier>(0xffffffff, 0xffffffff)</ParentIdentifier>
			<BoxIdentifier>(0x2c59bb68, 0x607f56d9)</BoxIdentifier>
			<NumChildren>0</NumChildren>
		</VisualisationWidget>
		<VisualisationWidget>
			<Identifier>(0x6243a39b, 0x1dcc39f1)</Identifier>
			<Type>3</Type>
			<ParentIdentifier>(0xffffffff, 0xffffffff)</ParentIdentifier>
			<BoxIdentifier>(0x563ffbad, 0x25b157d0)</BoxIdentifier>
			<NumChildren>0</NumChildren>
		</VisualisationWidget>
		<VisualisationWidget>
			<Identifier>(0x64a1c59d, 0x0acd6ae9)</Identifier>
			<Type>3</Type>
			<ParentIdentifier>(0xffffffff, 0xffffffff)</ParentIdentifier>
			<BoxIdentifier>(0x079b4a02, 0x73098828)</BoxIdentifier>
			<NumChildren>0</NumChildren>
		</VisualisationWidget>
		<VisualisationWidget>
			<Identifier>(0x6bbf151c, 0x7a0d6b68)</Identifier>
			<Type>3</Type>
			<ParentIdentifier>(0xffffffff, 0xffffffff)</ParentIdentifier>
			<BoxIdentifier>(0x5fd6c4c7, 0x21294a03)</BoxIdentifier>
			<NumChildren>0</NumChildren>
		</VisualisationWidget>
		<VisualisationWidget>
			<Identifier>(0x7d646a21, 0x30d3d8e3)</Identifier>
			<Type>3</Type>
			<ParentIdentifier>(0xffffffff, 0xffffffff)</ParentIdentifier>
			<BoxIdentifier>(0x3706b132, 0x00c4e50d)</BoxIdentifier>
			<NumChildren>0</NumChildren>
		</VisualisationWidget>
		<VisualisationWidget>
			<Identifier>(0x1d2f1c3e, 0x0f4d05d0)</Identifier>
			<Name>Default tab</Name>
			<Type>2</Type>
			<ParentIdentifier>(0x24600676, 0x41b79646)</ParentIdentifier>
			<Index>0</Index>
			<BoxIdentifier>(0xffffffff, 0xffffffff)</BoxIdentifier>
			<NumChildren>1</NumChildren>
		</VisualisationWidget>
		<VisualisationWidget>
			<Identifier>(0x4f9eb55c, 0x3741d097)</Identifier>
			<Type>3</Type>
			<ParentIdentifier>(0x1d2f1c3e, 0x0f4d05d0)</ParentIdentifier>
			<Index>0</Index>
			<BoxIdentifier>(0x1d5b71f3, 0x0427834b)</BoxIdentifier>
			<NumChildren>0</NumChildren>
		</VisualisationWidget>
	</VisualisationTree>
	<Attributes>
		<Attribute>
			<Identifier>(0x790d75b8, 0x3bb90c33)</Identifier>
			<Value></Value>
		</Attribute>
		<Attribute>
			<Identifier>(0x8c1fc55b, 0x7b433dc2)</Identifier>
			<Value>1.0</Value>
		</Attribute>
		<Attribute>
			<Identifier>(0x9f5c4075, 0x4a0d3666)</Identifier>
			<Value></Value>
		</Attribute>
		<Attribute>
			<Identifier>(0xf36a1567, 0xd13c53da)</Identifier>
			<Value>http://openvibe.inria.fr/p300-with-external-stimulator-tutorial/</Value>
		</Attribute>
		<Attribute>
			<Identifier>(0xf6b2e3fa, 0x7bd43926)</Identifier>
			<Value>p300-with-external-stimulator</Value>
		</Attribute>
		<Attribute>
			<Identifier>(0xf8034a49, 0x8b3f37cc)</Identifier>
			<Value>INRIA</Value>
		</Attribute>
	</Attributes>
</OpenViBE-Scenario>